{"Name":"EventCampaignMissionDetails_scream","MissionDetails":[{"ID":"ecm_scream_a_01","locNameKey":"ID_ECM_SCREAM_01_NAME","locDescriptionName":"ID_ECM_SCREAM_01_DESC","mapName":"Env_Jungle_merged","timeOfDay":"SUNSET","Settings":[{"Objectives":[{"ObjectiveEndStory":"ecm_scream_01_end","HealthPercent":25,"CantPersist":false,"Type":"WoundTarget"}],"Power":57479,"TotalHealth":131181,"CompactWave":[{"HeroId":"Scream","Power":19332,"Level":65,"GearLevel":9,"Loyalty":5,"RedStar":0,"Abilities":[6,5,5,4,0,0],"WavePosition":"s_0_wl_0_w_0_e_0"},{"HeroId":"Scream","Power":19157,"Level":65,"GearLevel":9,"Loyalty":5,"RedStar":0,"Abilities":[6,5,5,4,0,0],"WavePosition":"s_0_wl_0_w_1_e_0"},{"HeroId":"Scream","Power":18990,"Level":65,"GearLevel":9,"Loyalty":5,"RedStar":0,"Abilities":[6,5,5,4,0,0],"WavePosition":"s_0_wl_0_w_1_e_1"}],"PresetCharacters":[{"Description":null,"Expanded":false,"Waves":[{"Expanded":true,"InitialTurnFill":500,"TurnSpeed":1000,"MaxSlotFill":1,"MinSlotReq":0,"Entries":[{"abilities":[6,5,5,4,0,0],"useDefaultStats":false,"hero_id":"Scream","level":65,"loyalty":5,"tier":9,"desired_x_pos":1,"desired_y_pos":1,"stats_mod":{"crit_chance_pct":1}}],"StoryTellingID":"ecm_scream_01_start","EmptyStoryDelay":0,"HoldSpawnStory":true},{"Expanded":true,"TurnSpeed":1000,"MaxSlotFill":2,"MinSlotReq":0,"Entries":[{"abilities":[6,5,5,4,0,0],"useDefaultStats":false,"hero_id":"Scream","level":65,"loyalty":5,"tier":9,"desired_x_pos":2,"desired_y_pos":0,"stats_mod":{"speed":85}},{"abilities":[6,5,5,4,0,0],"useDefaultStats":false,"hero_id":"Scream","level":65,"loyalty":5,"tier":9,"desired_x_pos":0,"desired_y_pos":0,"stats_mod":{"speed":75}}],"EmptyStoryDelay":0,"HoldSpawnStory":false}]}]},{"Objectives":[{"CantPersist":false,"Type":"KillAll"}],"Power":60360,"TotalHealth":175888,"CompactWave":[{"HeroId":"Shocker","Power":9461,"Level":55,"GearLevel":6,"Loyalty":4,"RedStar":0,"Abilities":[5,5,4,3,0,0],"WavePosition":"s_1_wl_0_w_0_e_0"},{"HeroId":"UltSpiderMan","Power":8843,"Level":55,"GearLevel":6,"Loyalty":4,"RedStar":0,"Abilities":[5,5,4,1,0,0],"WavePosition":"s_1_wl_0_w_1_e_0"},{"HeroId":"UltSpiderMan","Power":8856,"Level":55,"GearLevel":6,"Loyalty":4,"RedStar":0,"Abilities":[5,5,4,1,0,0],"WavePosition":"s_1_wl_0_w_1_e_1"},{"HeroId":"Venom","Power":15110,"Level":60,"GearLevel":8,"Loyalty":5,"RedStar":0,"Abilities":[5,5,5,4,0,0],"WavePosition":"s_1_wl_0_w_2_e_0"},{"HeroId":"Carnage","Power":8603,"Level":55,"GearLevel":5,"Loyalty":4,"RedStar":0,"Abilities":[5,5,4,3,0,0],"WavePosition":"s_1_wl_0_w_2_e_1"},{"HeroId":"UltSpiderMan","Power":9487,"Level":55,"GearLevel":6,"Loyalty":4,"RedStar":0,"Abilities":[5,5,4,3,0,0],"WavePosition":"s_1_wl_0_w_2_e_2"}]}]},{"ID":"ecm_scream_a_02","locNameKey":"ID_ECM_SCREAM_02_NAME","locDescriptionName":"ID_ECM_SCREAM_02_DESC","mapName":"Env_Kree_Bridge_merged","timeOfDay":"NIGHT","Settings":[{"Objectives":[{"ObjectiveEndStory":"ecm_scream_02_end","CantPersist":false,"Type":"KillAll"}],"Power":15778,"TotalHealth":35665,"CompactWave":[{"HeroId":"Scream","Power":15778,"Level":59,"GearLevel":9,"Loyalty":4,"RedStar":0,"Abilities":[5,5,5,3,0,0],"WavePosition":"s_0_wl_0_w_0_e_0"}],"PresetCharacters":[{"Description":null,"Expanded":false,"Waves":[{"Expanded":true,"TurnSpeed":1000,"MaxSlotFill":5,"MinSlotReq":0,"Entries":[{"abilities":[5,5,5,3,0,0],"useDefaultStats":false,"hero_id":"Scream","level":59,"loyalty":4,"tier":9,"desired_x_pos":4,"desired_y_pos":0}],"StoryTellingID":"ecm_scream_02_start","EmptyStoryDelay":0,"HoldSpawnStory":false}]}]},{"Objectives":[{"CantPersist":false,"Type":"KillAll"}],"Power":162301,"TotalHealth":400912,"CompactWave":[{"HeroId":"KreeControl_Assist","Power":12093,"Level":59,"GearLevel":8,"Loyalty":4,"RedStar":0,"Abilities":[5,5,5,3,0,0],"WavePosition":"s_1_wl_0_w_0_e_0"},{"HeroId":"KreeControl_Assist","Power":12373,"Level":59,"GearLevel":8,"Loyalty":4,"RedStar":0,"Abilities":[5,5,5,3,0,0],"WavePosition":"s_1_wl_0_w_0_e_1"},{"HeroId":"KreeControl_Assist","Power":12240,"Level":59,"GearLevel":8,"Loyalty":4,"RedStar":0,"Abilities":[5,5,5,3,0,0],"WavePosition":"s_1_wl_0_w_0_e_2"},{"HeroId":"Ronan","Power":13828,"Level":59,"GearLevel":8,"Loyalty":4,"RedStar":0,"Abilities":[5,5,5,3,0,0],"WavePosition":"s_1_wl_0_w_0_e_3"},{"HeroId":"KreeDmg_Speed","Power":12106,"Level":59,"GearLevel":8,"Loyalty":4,"RedStar":0,"Abilities":[5,5,5,3,0,0],"WavePosition":"s_1_wl_0_w_0_e_4"},{"HeroId":"KreeDmg_Speed","Power":12384,"Level":59,"GearLevel":8,"Loyalty":4,"RedStar":0,"Abilities":[5,5,5,3,0,0],"WavePosition":"s_1_wl_0_w_0_e_5"},{"HeroId":"KreeDmg_Speed","Power":12252,"Level":59,"GearLevel":8,"Loyalty":4,"RedStar":0,"Abilities":[5,5,5,3,0,0],"WavePosition":"s_1_wl_0_w_0_e_6"},{"HeroId":"KreeTank_Counter","Power":12319,"Level":59,"GearLevel":8,"Loyalty":4,"RedStar":0,"Abilities":[5,5,5,3,0,0],"WavePosition":"s_1_wl_0_w_1_e_0"},{"HeroId":"KreeTank_Counter","Power":12508,"Level":59,"GearLevel":8,"Loyalty":4,"RedStar":0,"Abilities":[5,5,5,3,0,0],"WavePosition":"s_1_wl_0_w_1_e_1"},{"HeroId":"Korath","Power":13762,"Level":59,"GearLevel":8,"Loyalty":4,"RedStar":0,"Abilities":[5,5,5,3,0,0],"WavePosition":"s_1_wl_0_w_1_e_2"},{"HeroId":"KreeDmg_Offense","Power":12028,"Level":59,"GearLevel":8,"Loyalty":4,"RedStar":0,"Abilities":[5,5,5,3,0,0],"WavePosition":"s_1_wl_0_w_2_e_0"},{"HeroId":"KreeDmg_Offense","Power":12156,"Level":59,"GearLevel":8,"Loyalty":4,"RedStar":0,"Abilities":[5,5,5,3,0,0],"WavePosition":"s_1_wl_0_w_2_e_1"},{"HeroId":"KreeDmg_Speed","Power":12252,"Level":59,"GearLevel":8,"Loyalty":4,"RedStar":0,"Abilities":[5,5,5,3,0,0],"WavePosition":"s_1_wl_0_w_2_e_2"}]}]},{"ID":"ecm_scream_a_03","locNameKey":"ID_ECM_SCREAM_03_NAME","locDescriptionName":"ID_ECM_SCREAM_03_DESC","mapName":"Env_DestroyedCity_merged","timeOfDay":"DAY","Settings":[{"Objectives":[{"ObjectiveEndStory":"ecm_scream_03_end","CantPersist":false,"Type":"KillAll"}],"Power":16966,"TotalHealth":40168,"CompactWave":[{"HeroId":"Scream","Power":16966,"Level":60,"GearLevel":9,"Loyalty":5,"RedStar":0,"Abilities":[5,5,5,3,0,0],"WavePosition":"s_0_wl_0_w_0_e_0"}],"PresetCharacters":[{"Description":null,"Expanded":false,"Waves":[{"Expanded":true,"NextWaveIf":"AfterAllDead","TurnSpeed":1000,"MaxSlotFill":5,"MinSlotReq":0,"Entries":[{"abilities":[5,5,5,3,0,0],"useDefaultStats":false,"hero_id":"Scream","level":60,"loyalty":5,"tier":9,"desired_x_pos":4,"desired_y_pos":0}],"StoryTellingID":"ecm_scream_03_start","EmptyStoryDelay":0,"HoldSpawnStory":false}]}]},{"Power":171900,"TotalHealth":531202,"CompactWave":[{"HeroId":"Scream","Power":16685,"Level":60,"GearLevel":9,"Loyalty":5,"RedStar":0,"Abilities":[5,5,5,3,0,0],"WavePosition":"s_1_wl_0_w_0_e_0"},{"HeroId":"Scream","Power":16966,"Level":60,"GearLevel":9,"Loyalty":5,"RedStar":0,"Abilities":[5,5,5,3,0,0],"WavePosition":"s_1_wl_0_w_0_e_1"},{"HeroId":"Venom","Power":13931,"Level":60,"GearLevel":8,"Loyalty":4,"RedStar":0,"Abilities":[5,5,5,3,0,0],"WavePosition":"s_1_wl_0_w_0_e_2"},{"HeroId":"Carnage","Power":14242,"Level":60,"GearLevel":8,"Loyalty":4,"RedStar":0,"Abilities":[5,5,5,3,0,0],"WavePosition":"s_1_wl_0_w_0_e_3"},{"HeroId":"Deadpool","Power":16420,"Level":60,"GearLevel":9,"Loyalty":5,"RedStar":0,"Abilities":[5,5,5,3,0,0],"WavePosition":"s_1_wl_0_w_0_e_4"},{"HeroId":"Deadpool","Power":16657,"Level":60,"GearLevel":9,"Loyalty":5,"RedStar":0,"Abilities":[5,5,5,3,0,0],"WavePosition":"s_1_wl_0_w_0_e_5"},{"HeroId":"AntiVenom","Power":18436,"Level":60,"GearLevel":9,"Loyalty":5,"RedStar":0,"Abilities":[5,5,5,3,0,0],"WavePosition":"s_1_wl_0_w_1_e_0"},{"HeroId":"RocketRaccoon","Power":13657,"Level":60,"GearLevel":8,"Loyalty":4,"RedStar":0,"Abilities":[5,5,5,3,0,0],"WavePosition":"s_1_wl_0_w_1_e_1"},{"HeroId":"RocketRaccoon","Power":13845,"Level":60,"GearLevel":8,"Loyalty":4,"RedStar":0,"Abilities":[5,5,5,3,0,0],"WavePosition":"s_1_wl_0_w_1_e_2"},{"HeroId":"Groot","Power":13764,"Level":60,"GearLevel":8,"Loyalty":4,"RedStar":0,"Abilities":[5,5,5,3,0,0],"WavePosition":"s_1_wl_0_w_1_e_3"},{"HeroId":"Drax","Power":17297,"Level":61,"GearLevel":9,"Loyalty":5,"RedStar":0,"Abilities":[5,5,5,4,0,0],"WavePosition":"s_1_wl_0_w_1_e_4"}]}]},{"ID":"ecm_scream_a_04","locNameKey":"ID_ECM_SCREAM_04_NAME","locDescriptionName":"ID_ECM_SCREAM_04_DESC","mapName":"Env_HellsKitchen_Alleyway_merged","timeOfDay":"NIGHT","Settings":[{"Objectives":[{"ObjectiveEndStory":"ecm_scream_04_end","CantPersist":false,"Type":"KillAll"}],"Power":16966,"TotalHealth":40168,"CompactWave":[{"HeroId":"Scream","Power":16966,"Level":60,"GearLevel":9,"Loyalty":5,"RedStar":0,"Abilities":[5,5,5,3,0,0],"WavePosition":"s_0_wl_0_w_0_e_0"}],"PresetCharacters":[{"Description":null,"Expanded":false,"Waves":[{"Expanded":true,"TurnSpeed":1000,"MaxSlotFill":2,"MinSlotReq":0,"Entries":[{"abilities":[5,5,5,3,0,0],"useDefaultStats":false,"hero_id":"Scream","level":60,"loyalty":5,"tier":9,"desired_x_pos":4,"desired_y_pos":0}],"StoryTellingID":"ecm_scream_04_start","EmptyStoryDelay":0,"HoldSpawnStory":false}]}]},{"Objectives":[{"CantPersist":false,"Type":"KillAll"}],"Power":168129,"TotalHealth":445643,"CompactWave":[{"HeroId":"Crossbones","Power":17042,"Level":60,"GearLevel":9,"Loyalty":5,"RedStar":0,"Abilities":[5,5,5,4,0,0],"WavePosition":"s_1_wl_0_w_0_e_0"},{"HeroId":"Crossbones","Power":17304,"Level":60,"GearLevel":9,"Loyalty":5,"RedStar":0,"Abilities":[5,5,5,4,0,0],"WavePosition":"s_1_wl_0_w_0_e_1"},{"HeroId":"AntMan","Power":17093,"Level":60,"GearLevel":9,"Loyalty":5,"RedStar":0,"Abilities":[5,5,5,4,0,0],"WavePosition":"s_1_wl_0_w_0_e_2"},{"HeroId":"Wasp","Power":17038,"Level":60,"GearLevel":9,"Loyalty":5,"RedStar":0,"Abilities":[5,5,5,4,0,0],"WavePosition":"s_1_wl_0_w_0_e_3"},{"HeroId":"Wasp","Power":17304,"Level":60,"GearLevel":9,"Loyalty":5,"RedStar":0,"Abilities":[5,5,5,4,0,0],"WavePosition":"s_1_wl_0_w_0_e_4"},{"HeroId":"Cable","Power":17315,"Level":60,"GearLevel":9,"Loyalty":5,"RedStar":0,"Abilities":[5,5,5,4,0,0],"WavePosition":"s_1_wl_0_w_0_e_5"},{"HeroId":"Negasonic","Power":15567,"Level":60,"GearLevel":9,"Loyalty":5,"RedStar":0,"Abilities":[5,5,4,3,0,0],"WavePosition":"s_1_wl_0_w_1_e_0"},{"HeroId":"X23","Power":16062,"Level":60,"GearLevel":9,"Loyalty":5,"RedStar":0,"Abilities":[5,5,4,3,0,0],"WavePosition":"s_1_wl_0_w_1_e_1"},{"HeroId":"Domino","Power":16747,"Level":60,"GearLevel":9,"Loyalty":5,"RedStar":0,"Abilities":[5,5,5,3,0,0],"WavePosition":"s_1_wl_0_w_1_e_2"},{"HeroId":"Deadpool","Power":16657,"Level":60,"GearLevel":9,"Loyalty":5,"RedStar":0,"Abilities":[5,5,5,3,0,0],"WavePosition":"s_1_wl_0_w_1_e_3"}]}]},{"ID":"ecm_scream_a_05","locNameKey":"ID_ECM_SCREAM_05_NAME","locDescriptionName":"ID_ECM_SCREAM_05_DESC","mapName":"Env_Warehouse_merged","timeOfDay":"DAY","Settings":[{"Objectives":[{"ObjectiveEndStory":"ecm_scream_05_end","CantPersist":false,"Type":"KillAll"}],"Power":17711,"TotalHealth":40857,"CompactWave":[{"HeroId":"Scream","Power":17711,"Level":61,"GearLevel":9,"Loyalty":5,"RedStar":0,"Abilities":[5,5,5,4,0,0],"WavePosition":"s_0_wl_0_w_0_e_0"}],"PresetCharacters":[{"Description":null,"Expanded":false,"Waves":[{"Expanded":true,"TurnSpeed":1000,"MaxSlotFill":2,"MinSlotReq":0,"Entries":[{"abilities":[5,5,5,4,0,0],"hero_id":"Scream","level":61,"loyalty":5,"tier":9,"desired_x_pos":4,"desired_y_pos":0}],"StoryTellingID":"ecm_scream_05_start","EmptyStoryDelay":0,"HoldSpawnStory":false}]}]},{"Objectives":[{"ObjectiveEndStory":"ecm_scream_05_end","CantPersist":false,"Type":"KillAll"}],"Power":223601,"TotalHealth":819940,"CompactWave":[{"HeroId":"InvisibleWoman","Power":18641,"Level":61,"GearLevel":9,"Loyalty":5,"RedStar":0,"PercentageEquippedGear":50,"Abilities":[5,5,5,4,0,0],"WavePosition":"s_1_wl_0_w_0_e_0"},{"HeroId":"MrFantastic","Power":18536,"Level":61,"GearLevel":9,"Loyalty":5,"RedStar":0,"PercentageEquippedGear":50,"Abilities":[5,5,5,4,0,0],"WavePosition":"s_1_wl_0_w_0_e_1"},{"HeroId":"Namor","Power":18441,"Level":61,"GearLevel":9,"Loyalty":5,"RedStar":0,"PercentageEquippedGear":50,"Abilities":[5,5,5,4,0,0],"WavePosition":"s_1_wl_0_w_0_e_2"},{"HeroId":"Namor","Power":18840,"Level":61,"GearLevel":9,"Loyalty":5,"RedStar":0,"PercentageEquippedGear":50,"Abilities":[5,5,5,4,0,0],"WavePosition":"s_1_wl_0_w_0_e_3"},{"HeroId":"ShieldSupport_Stealth","Power":16802,"Level":61,"GearLevel":9,"Loyalty":5,"RedStar":0,"PercentageEquippedGear":50,"Abilities":[5,5,5,4,0,0],"WavePosition":"s_1_wl_0_w_0_e_4"},{"HeroId":"ShieldSupport_Heal","Power":16742,"Level":61,"GearLevel":9,"Loyalty":5,"RedStar":0,"PercentageEquippedGear":50,"Abilities":[5,5,5,4,0,0],"WavePosition":"s_1_wl_0_w_0_e_5"},{"HeroId":"Thing","Power":20070,"Level":62,"GearLevel":10,"Loyalty":5,"RedStar":0,"Abilities":[5,5,5,4,0,0],"WavePosition":"s_1_wl_0_w_1_e_0"},{"HeroId":"Thing","Power":18996,"Level":62,"GearLevel":9,"Loyalty":5,"RedStar":0,"PercentageEquippedGear":50,"Abilities":[5,5,5,4,0,0],"WavePosition":"s_1_wl_0_w_1_e_1"},{"HeroId":"HumanTorch","Power":20055,"Level":62,"GearLevel":10,"Loyalty":5,"RedStar":0,"Abilities":[5,5,5,4,0,0],"WavePosition":"s_1_wl_0_w_1_e_2"},{"HeroId":"HumanTorch","Power":18925,"Level":62,"GearLevel":9,"Loyalty":5,"RedStar":0,"PercentageEquippedGear":50,"Abilities":[5,5,5,4,0,0],"WavePosition":"s_1_wl_0_w_1_e_3"},{"HeroId":"ShieldTank_Stun","Power":16883,"Level":62,"GearLevel":9,"Loyalty":5,"RedStar":0,"PercentageEquippedGear":50,"Abilities":[5,5,5,4,0,0],"WavePosition":"s_1_wl_0_w_1_e_4"},{"HeroId":"Namor","Power":20670,"Level":62,"GearLevel":10,"Loyalty":5,"RedStar":0,"Abilities":[5,5,5,4,0,0],"WavePosition":"s_1_wl_0_w_1_e_5"}]}]},{"ID":"ecm_scream_a_06","locNameKey":"ID_ECM_SCREAM_06_NAME","locDescriptionName":"ID_ECM_SCREAM_06_DESC","mapName":"Env_Bunker_Storage_merged","timeOfDay":"SUNSET","Settings":[{"Objectives":[{"ObjectiveEndStory":"ecm_scream_06_end","HealthPercent":25,"CantPersist":false,"Type":"WoundTarget"}],"Power":17937,"TotalHealth":41557,"CompactWave":[{"HeroId":"Scream","Power":17937,"Level":62,"GearLevel":9,"Loyalty":5,"RedStar":0,"Abilities":[5,5,5,4,0,0],"WavePosition":"s_0_wl_0_w_0_e_0"}],"PresetCharacters":[{"Description":null,"Expanded":false,"Waves":[{"Expanded":true,"TurnSpeed":1000,"MaxSlotFill":1,"MinSlotReq":0,"Entries":[{"abilities":[5,5,5,4,0,0],"hero_id":"Scream","level":62,"loyalty":5,"tier":9,"desired_x_pos":4,"desired_y_pos":0}],"EmptyStoryDelay":0,"HoldSpawnStory":false}]}]},{"Objectives":[{"HealthPercent":25,"CantPersist":false,"Type":"WoundTarget"}],"Power":258248,"TotalHealth":726510,"CompactWave":[{"HeroId":"Rescue","Power":17885,"Level":62,"GearLevel":9,"Loyalty":5,"RedStar":0,"Abilities":[5,5,5,4,0,0],"WavePosition":"s_1_wl_0_w_0_e_0"},{"HeroId":"Rescue","Power":17885,"Level":62,"GearLevel":9,"Loyalty":5,"RedStar":0,"Abilities":[5,5,5,4,0,0],"WavePosition":"s_1_wl_0_w_0_e_1"},{"HeroId":"Falcon","Power":17775,"Level":62,"GearLevel":9,"Loyalty":5,"RedStar":0,"Abilities":[5,5,5,4,0,0],"WavePosition":"s_1_wl_0_w_0_e_2"},{"HeroId":"Ironheart","Power":17980,"Level":62,"GearLevel":9,"Loyalty":5,"RedStar":0,"Abilities":[5,5,5,4,0,0],"WavePosition":"s_1_wl_0_w_0_e_3"},{"HeroId":"WarMachine","Power":17705,"Level":62,"GearLevel":9,"Loyalty":5,"RedStar":0,"Abilities":[5,5,5,4,0,0],"WavePosition":"s_1_wl_0_w_0_e_4"},{"HeroId":"WarMachine","Power":17705,"Level":62,"GearLevel":9,"Loyalty":5,"RedStar":0,"Abilities":[5,5,5,4,0,0],"WavePosition":"s_1_wl_0_w_0_e_5"},{"HeroId":"CaptainAmerica","Power":18564,"Level":62,"GearLevel":9,"Loyalty":5,"RedStar":0,"PercentageEquippedGear":50,"Abilities":[5,5,5,4,0,0],"WavePosition":"s_1_wl_0_w_1_e_0"},{"HeroId":"Rescue","Power":18496,"Level":62,"GearLevel":9,"Loyalty":5,"RedStar":0,"PercentageEquippedGear":50,"Abilities":[5,5,5,4,0,0],"WavePosition":"s_1_wl_0_w_1_e_1"},{"HeroId":"Ironheart","Power":18598,"Level":62,"GearLevel":9,"Loyalty":5,"RedStar":0,"PercentageEquippedGear":50,"Abilities":[5,5,5,4,0,0],"WavePosition":"s_1_wl_0_w_1_e_2"},{"HeroId":"IronMan","Power":20108,"Level":62,"GearLevel":9,"Loyalty":5,"RedStar":0,"PercentageEquippedGear":50,"Abilities":[5,5,5,4,0,0],"WavePosition":"s_1_wl_0_w_1_e_3"},{"HeroId":"Colossus","Power":18530,"Level":62,"GearLevel":9,"Loyalty":5,"RedStar":0,"PercentageEquippedGear":50,"Abilities":[5,5,5,4,0,0],"WavePosition":"s_1_wl_0_w_2_e_0"},{"HeroId":"Psylocke","Power":18543,"Level":62,"GearLevel":9,"Loyalty":5,"RedStar":0,"PercentageEquippedGear":50,"Abilities":[5,5,5,4,0,0],"WavePosition":"s_1_wl_0_w_2_e_1"},{"HeroId":"Mantis","Power":18392,"Level":62,"GearLevel":9,"Loyalty":5,"RedStar":0,"PercentageEquippedGear":50,"Abilities":[5,5,5,4,0,0],"WavePosition":"s_1_wl_0_w_2_e_2"},{"HeroId":"Cyclops","Power":20082,"Level":62,"GearLevel":10,"Loyalty":5,"RedStar":0,"Abilities":[5,5,5,4,0,0],"WavePosition":"s_1_wl_0_w_3_e_0"}]}]},{"ID":"ecm_scream_a_07","locNameKey":"ID_ECM_SCREAM_07_NAME","locDescriptionName":"ID_ECM_SCREAM_07_DESC","mapName":"Env_Bunker_Storage_merged","timeOfDay":"SUNSET","Settings":[{"Objectives":[{"ObjectiveEndStory":"ecm_scream_07_end","CantPersist":false,"Type":"KillAll"}],"Power":18166,"TotalHealth":42269,"CompactWave":[{"HeroId":"Scream","Power":18166,"Level":63,"GearLevel":9,"Loyalty":5,"RedStar":0,"Abilities":[5,5,5,4,0,0],"WavePosition":"s_0_wl_0_w_0_e_0"}],"PresetCharacters":[{"Description":null,"Expanded":false,"Waves":[{"Expanded":true,"TurnSpeed":1000,"MaxSlotFill":1,"MinSlotReq":0,"Entries":[{"abilities":[5,5,5,4,0,0],"hero_id":"Scream","level":63,"loyalty":5,"tier":9,"desired_x_pos":4,"desired_y_pos":0}],"EmptyStoryDelay":0,"HoldSpawnStory":false}]}]},{"Objectives":[{"CantPersist":false,"Type":"KillAll"}],"Power":232400,"TotalHealth":535491,"CompactWave":[{"HeroId":"IronMan","Power":18119,"Level":63,"GearLevel":9,"Loyalty":5,"RedStar":0,"Abilities":[5,5,5,4,0,0],"WavePosition":"s_1_wl_0_w_0_e_0"},{"HeroId":"Crystal","Power":21556,"Level":63,"GearLevel":9,"Loyalty":5,"RedStar":0,"PercentageEquippedGear":50,"Abilities":[6,6,6,4,0,0],"WavePosition":"s_1_wl_0_w_1_e_0"},{"HeroId":"Quake","Power":20730,"Level":63,"GearLevel":9,"Loyalty":5,"RedStar":0,"PercentageEquippedGear":50,"Abilities":[6,6,6,4,0,0],"WavePosition":"s_1_wl_0_w_1_e_1"},{"HeroId":"Quake","Power":20990,"Level":63,"GearLevel":9,"Loyalty":5,"RedStar":0,"PercentageEquippedGear":50,"Abilities":[6,6,6,4,0,0],"WavePosition":"s_1_wl_0_w_1_e_2"},{"HeroId":"YoYo","Power":21801,"Level":63,"GearLevel":9,"Loyalty":5,"RedStar":0,"PercentageEquippedGear":50,"Abilities":[6,6,6,4,0,0],"WavePosition":"s_1_wl_0_w_1_e_3"},{"HeroId":"Yondu","Power":21231,"Level":63,"GearLevel":9,"Loyalty":5,"RedStar":0,"PercentageEquippedGear":50,"Abilities":[6,6,6,4,0,0],"WavePosition":"s_1_wl_0_w_1_e_4"},{"HeroId":"Karnak","Power":21598,"Level":63,"GearLevel":9,"Loyalty":5,"RedStar":0,"PercentageEquippedGear":50,"Abilities":[6,6,6,4,0,0],"WavePosition":"s_1_wl_0_w_2_e_0"},{"HeroId":"YoYo","Power":18877,"Level":63,"GearLevel":9,"Loyalty":5,"RedStar":0,"PercentageEquippedGear":50,"Abilities":[5,5,5,4,0,0],"WavePosition":"s_1_wl_0_w_2_e_1"},{"HeroId":"Crystal","Power":18665,"Level":63,"GearLevel":9,"Loyalty":5,"RedStar":0,"PercentageEquippedGear":50,"Abilities":[5,5,5,4,0,0],"WavePosition":"s_1_wl_0_w_2_e_2"},{"HeroId":"KreeSupport_HoT","Power":16399,"Level":63,"GearLevel":9,"Loyalty":5,"RedStar":0,"Abilities":[5,5,5,4,0,0],"WavePosition":"s_1_wl_0_w_2_e_3"},{"HeroId":"KreeDmg_Speed","Power":16105,"Level":63,"GearLevel":9,"Loyalty":5,"RedStar":0,"Abilities":[5,5,5,4,0,0],"WavePosition":"s_1_wl_0_w_2_e_4"},{"HeroId":"KreeDmg_Speed","Power":16329,"Level":63,"GearLevel":9,"Loyalty":5,"RedStar":0,"Abilities":[5,5,5,4,0,0],"WavePosition":"s_1_wl_0_w_2_e_5"}]}]},{"ID":"ecm_scream_a_08","locNameKey":"ID_ECM_SCREAM_08_NAME","locDescriptionName":"ID_ECM_SCREAM_08_DESC","mapName":"Env_Hydra_Base_merged","timeOfDay":"SUNSET","Settings":[{"Objectives":[{"ObjectiveEndStory":"ecm_scream_08_end","CantPersist":false,"Type":"KillAll"}],"Power":22971,"TotalHealth":58098,"CompactWave":[{"HeroId":"Scream","Power":22971,"Level":64,"GearLevel":10,"Loyalty":6,"RedStar":0,"Abilities":[6,5,5,4,0,0],"WavePosition":"s_0_wl_0_w_0_e_0"}],"PresetCharacters":[{"Description":null,"Expanded":false,"Waves":[{"Expanded":true,"TurnSpeed":1000,"MaxSlotFill":1,"MinSlotReq":0,"Entries":[{"abilities":[6,5,5,4,0,0],"useDefaultStats":false,"hero_id":"Scream","level":64,"loyalty":6,"tier":10,"desired_x_pos":4,"desired_y_pos":0,"stats_mod":{"max_hp":115,"damage":115}}],"EmptyStoryDelay":0,"HoldSpawnStory":false}]}]},{"Objectives":[{"CantPersist":false,"Type":"KillAll"}],"Power":276223,"TotalHealth":734117,"CompactWave":[{"HeroId":"DoctorStrange","Power":24452,"Level":64,"GearLevel":10,"Loyalty":5,"RedStar":0,"PercentageEquippedGear":50,"Abilities":[6,6,6,5,0,0],"WavePosition":"s_1_wl_0_w_0_e_0"},{"HeroId":"GhostRider","Power":25892,"Level":64,"GearLevel":10,"Loyalty":5,"RedStar":0,"PercentageEquippedGear":50,"Abilities":[6,6,6,5,0,0],"WavePosition":"s_1_wl_0_w_0_e_1"},{"HeroId":"BaronMordo","Power":24771,"Level":64,"GearLevel":10,"Loyalty":5,"RedStar":0,"PercentageEquippedGear":50,"Abilities":[6,6,6,5,0,0],"WavePosition":"s_1_wl_0_w_0_e_2"},{"HeroId":"ElsaBloodstone","Power":25050,"Level":64,"GearLevel":10,"Loyalty":5,"RedStar":0,"PercentageEquippedGear":50,"Abilities":[6,6,6,5,0,0],"WavePosition":"s_1_wl_0_w_0_e_3"},{"HeroId":"ElsaBloodstone","Power":25050,"Level":64,"GearLevel":10,"Loyalty":5,"RedStar":0,"PercentageEquippedGear":50,"Abilities":[6,6,6,5,0,0],"WavePosition":"s_1_wl_0_w_0_e_4"},{"HeroId":"Drax","Power":24904,"Level":64,"GearLevel":10,"Loyalty":5,"RedStar":0,"PercentageEquippedGear":50,"Abilities":[6,6,6,5,0,0],"WavePosition":"s_1_wl_0_w_0_e_5"},{"HeroId":"ScarletWitch","Power":24776,"Level":64,"GearLevel":10,"Loyalty":5,"RedStar":0,"PercentageEquippedGear":50,"Abilities":[6,6,6,5,0,0],"WavePosition":"s_1_wl_0_w_1_e_0"},{"HeroId":"ElsaBloodstone","Power":25297,"Level":64,"GearLevel":10,"Loyalty":5,"RedStar":0,"PercentageEquippedGear":50,"Abilities":[6,6,6,5,0,0],"WavePosition":"s_1_wl_0_w_1_e_1"},{"HeroId":"Thing","Power":25376,"Level":64,"GearLevel":10,"Loyalty":5,"RedStar":0,"PercentageEquippedGear":50,"Abilities":[6,6,6,5,0,0],"WavePosition":"s_1_wl_0_w_1_e_2"},{"HeroId":"MrSinister","Power":25884,"Level":64,"GearLevel":10,"Loyalty":5,"RedStar":0,"PercentageEquippedGear":50,"Abilities":[6,6,6,5,0,0],"WavePosition":"s_1_wl_0_w_2_e_0"},{"HeroId":"BaronMordo","Power":24771,"Level":64,"GearLevel":10,"Loyalty":5,"RedStar":0,"PercentageEquippedGear":50,"Abilities":[6,6,6,5,0,0],"WavePosition":"s_1_wl_0_w_2_e_1"}]}]},{"ID":"ecm_scream_a_09","locNameKey":"ID_ECM_SCREAM_09_NAME","locDescriptionName":"ID_ECM_SCREAM_09_DESC","mapName":"Env_Hydra_Base_merged","timeOfDay":"SUNSET","Settings":[{"Objectives":[{"ObjectiveEndStory":"ecm_scream_09_end","CantPersist":false,"Type":"KillAll"}],"Power":19931,"TotalHealth":65590,"CompactWave":[{"HeroId":"Scream","Power":19931,"Level":65,"GearLevel":9,"Loyalty":5,"RedStar":0,"Abilities":[6,5,5,4,0,0],"WavePosition":"s_0_wl_0_w_0_e_0"}],"PresetCharacters":[{"Description":null,"Expanded":false,"Waves":[{"Expanded":true,"TurnSpeed":1000,"MaxSlotFill":1,"MinSlotReq":0,"Entries":[{"abilities":[6,5,5,4,0,0],"hero_id":"Scream","level":65,"loyalty":5,"tier":9,"desired_x_pos":4,"desired_y_pos":0,"stats_mod":{"resistance":102,"max_hp":150,"damage":105}}],"EmptyStoryDelay":0,"HoldSpawnStory":false}]}]},{"Objectives":[{"CantPersist":false,"Type":"KillAll"}],"Power":231693,"TotalHealth":606347,"CompactWave":[{"HeroId":"BlackBolt","Power":21074,"Level":65,"GearLevel":9,"Loyalty":5,"RedStar":0,"Abilities":[6,5,5,4,0,0],"WavePosition":"s_1_wl_0_w_0_e_0"},{"HeroId":"WarMachine","Power":19023,"Level":65,"GearLevel":9,"Loyalty":5,"RedStar":0,"Abilities":[6,5,5,4,0,0],"WavePosition":"s_1_wl_0_w_0_e_1"},{"HeroId":"WarMachine","Power":19023,"Level":65,"GearLevel":9,"Loyalty":5,"RedStar":0,"Abilities":[6,5,5,4,0,0],"WavePosition":"s_1_wl_0_w_0_e_2"},{"HeroId":"Magneto","Power":19260,"Level":65,"GearLevel":9,"Loyalty":5,"RedStar":0,"Abilities":[6,5,5,4,0,0],"WavePosition":"s_1_wl_0_w_0_e_3"},{"HeroId":"Minerva","Power":19228,"Level":65,"GearLevel":9,"Loyalty":5,"RedStar":0,"Abilities":[6,5,5,4,0,0],"WavePosition":"s_1_wl_0_w_0_e_4"},{"HeroId":"Quake","Power":18777,"Level":65,"GearLevel":9,"Loyalty":5,"RedStar":0,"Abilities":[6,5,5,4,0,0],"WavePosition":"s_1_wl_0_w_0_e_5"},{"HeroId":"Quake","Power":18777,"Level":65,"GearLevel":9,"Loyalty":5,"RedStar":0,"Abilities":[6,5,5,4,0,0],"WavePosition":"s_1_wl_0_w_0_e_6"},{"HeroId":"Crystal","Power":19282,"Level":65,"GearLevel":9,"Loyalty":5,"RedStar":0,"Abilities":[6,5,5,4,0,0],"WavePosition":"s_1_wl_0_w_0_e_7"},{"HeroId":"Minerva","Power":19228,"Level":65,"GearLevel":9,"Loyalty":5,"RedStar":0,"Abilities":[6,5,5,4,0,0],"WavePosition":"s_1_wl_0_w_1_e_0"},{"HeroId":"Phoenix","Power":19365,"Level":65,"GearLevel":9,"Loyalty":5,"RedStar":0,"Abilities":[6,5,5,4,0,0],"WavePosition":"s_1_wl_0_w_1_e_1"},{"HeroId":"YoYo","Power":19156,"Level":65,"GearLevel":9,"Loyalty":5,"RedStar":0,"Abilities":[6,5,5,4,0,0],"WavePosition":"s_1_wl_0_w_1_e_2"},{"HeroId":"YoYo","Power":19500,"Level":65,"GearLevel":9,"Loyalty":5,"RedStar":0,"Abilities":[6,5,5,4,0,0],"WavePosition":"s_1_wl_0_w_1_e_3"}]}]},{"ID":"ecm_scream_b_01","locNameKey":"ID_ECM_SCREAM_01_NAME","locDescriptionName":"ID_ECM_SCREAM_01_DESC","mapName":"Env_Jungle_merged","timeOfDay":"SUNSET","Settings":[{"Objectives":[{"ObjectiveEndStory":"ecm_scream_01_end","HealthPercent":25,"CantPersist":false,"Type":"WoundTarget"}],"Power":57479,"TotalHealth":131181,"CompactWave":[{"HeroId":"Scream","Power":19332,"Level":65,"GearLevel":9,"Loyalty":5,"RedStar":0,"Abilities":[6,5,5,4,0,0],"WavePosition":"s_0_wl_0_w_0_e_0"},{"HeroId":"Scream","Power":19157,"Level":65,"GearLevel":9,"Loyalty":5,"RedStar":0,"Abilities":[6,5,5,4,0,0],"WavePosition":"s_0_wl_0_w_1_e_0"},{"HeroId":"Scream","Power":18990,"Level":65,"GearLevel":9,"Loyalty":5,"RedStar":0,"Abilities":[6,5,5,4,0,0],"WavePosition":"s_0_wl_0_w_1_e_1"}],"PresetCharacters":[{"Description":null,"Expanded":false,"Waves":[{"Expanded":true,"InitialTurnFill":500,"TurnSpeed":1000,"MaxSlotFill":1,"MinSlotReq":0,"Entries":[{"abilities":[6,5,5,4,0,0],"useDefaultStats":false,"hero_id":"Scream","level":65,"loyalty":5,"tier":9,"desired_x_pos":1,"desired_y_pos":1,"stats_mod":{"crit_chance_pct":1}}],"StoryTellingID":"ecm_scream_01_start","EmptyStoryDelay":0,"HoldSpawnStory":true},{"Expanded":true,"TurnSpeed":1000,"MaxSlotFill":2,"MinSlotReq":0,"Entries":[{"abilities":[6,5,5,4,0,0],"useDefaultStats":false,"hero_id":"Scream","level":65,"loyalty":5,"tier":9,"desired_x_pos":2,"desired_y_pos":0,"stats_mod":{"speed":85}},{"abilities":[6,5,5,4,0,0],"useDefaultStats":false,"hero_id":"Scream","level":65,"loyalty":5,"tier":9,"desired_x_pos":0,"desired_y_pos":0,"stats_mod":{"speed":75}}],"EmptyStoryDelay":0,"HoldSpawnStory":false}]}]},{"Objectives":[{"CantPersist":false,"Type":"KillAll"}],"Power":60360,"TotalHealth":175888,"CompactWave":[{"HeroId":"Shocker","Power":9461,"Level":55,"GearLevel":6,"Loyalty":4,"RedStar":0,"Abilities":[5,5,4,3,0,0],"WavePosition":"s_1_wl_0_w_0_e_0"},{"HeroId":"UltSpiderMan","Power":8843,"Level":55,"GearLevel":6,"Loyalty":4,"RedStar":0,"Abilities":[5,5,4,1,0,0],"WavePosition":"s_1_wl_0_w_1_e_0"},{"HeroId":"UltSpiderMan","Power":8856,"Level":55,"GearLevel":6,"Loyalty":4,"RedStar":0,"Abilities":[5,5,4,1,0,0],"WavePosition":"s_1_wl_0_w_1_e_1"},{"HeroId":"Venom","Power":15110,"Level":60,"GearLevel":8,"Loyalty":5,"RedStar":0,"Abilities":[5,5,5,4,0,0],"WavePosition":"s_1_wl_0_w_2_e_0"},{"HeroId":"Carnage","Power":8603,"Level":55,"GearLevel":5,"Loyalty":4,"RedStar":0,"Abilities":[5,5,4,3,0,0],"WavePosition":"s_1_wl_0_w_2_e_1"},{"HeroId":"UltSpiderMan","Power":9487,"Level":55,"GearLevel":6,"Loyalty":4,"RedStar":0,"Abilities":[5,5,4,3,0,0],"WavePosition":"s_1_wl_0_w_2_e_2"}]}]},{"ID":"ecm_scream_b_02","locNameKey":"ID_ECM_SCREAM_02_NAME","locDescriptionName":"ID_ECM_SCREAM_02_DESC","mapName":"Env_Kree_Bridge_merged","timeOfDay":"NIGHT","Settings":[{"Objectives":[{"ObjectiveEndStory":"ecm_scream_02_end","CantPersist":false,"Type":"KillAll"}],"Power":6763,"TotalHealth":16794,"CompactWave":[{"HeroId":"Scream","Power":6763,"Level":43,"GearLevel":7,"Loyalty":3,"RedStar":0,"Abilities":[4,4,3,2,0,0],"WavePosition":"s_0_wl_0_w_0_e_0"}],"PresetCharacters":[{"Description":null,"Expanded":false,"Waves":[{"Expanded":true,"TurnSpeed":1000,"MaxSlotFill":5,"MinSlotReq":0,"Entries":[{"abilities":[4,4,3,2,0,0],"useDefaultStats":false,"hero_id":"Scream","level":43,"loyalty":3,"tier":7,"desired_x_pos":4,"desired_y_pos":0}],"StoryTellingID":"ecm_scream_02_start","EmptyStoryDelay":0,"HoldSpawnStory":false}]}]},{"Objectives":[{"CantPersist":false,"Type":"KillAll"}],"Power":82892,"TotalHealth":205861,"CompactWave":[{"HeroId":"KreeControl_Assist","Power":6320,"Level":43,"GearLevel":7,"Loyalty":3,"RedStar":0,"Abilities":[4,4,3,2,0,0],"WavePosition":"s_1_wl_0_w_0_e_0"},{"HeroId":"KreeControl_Assist","Power":6320,"Level":43,"GearLevel":7,"Loyalty":3,"RedStar":0,"Abilities":[4,4,3,2,0,0],"WavePosition":"s_1_wl_0_w_0_e_1"},{"HeroId":"KreeControl_Assist","Power":6320,"Level":43,"GearLevel":7,"Loyalty":3,"RedStar":0,"Abilities":[4,4,3,2,0,0],"WavePosition":"s_1_wl_0_w_0_e_2"},{"HeroId":"Ronan","Power":6616,"Level":43,"GearLevel":7,"Loyalty":3,"RedStar":0,"Abilities":[4,4,3,2,0,0],"WavePosition":"s_1_wl_0_w_0_e_3"},{"HeroId":"KreeDmg_Speed","Power":6324,"Level":43,"GearLevel":7,"Loyalty":3,"RedStar":0,"Abilities":[4,4,3,2,0,0],"WavePosition":"s_1_wl_0_w_0_e_4"},{"HeroId":"KreeDmg_Speed","Power":6324,"Level":43,"GearLevel":7,"Loyalty":3,"RedStar":0,"Abilities":[4,4,3,2,0,0],"WavePosition":"s_1_wl_0_w_0_e_5"},{"HeroId":"KreeDmg_Speed","Power":6324,"Level":43,"GearLevel":7,"Loyalty":3,"RedStar":0,"Abilities":[4,4,3,2,0,0],"WavePosition":"s_1_wl_0_w_0_e_6"},{"HeroId":"KreeTank_Counter","Power":6433,"Level":43,"GearLevel":7,"Loyalty":3,"RedStar":0,"Abilities":[4,4,3,2,0,0],"WavePosition":"s_1_wl_0_w_1_e_0"},{"HeroId":"KreeTank_Counter","Power":6433,"Level":43,"GearLevel":7,"Loyalty":3,"RedStar":0,"Abilities":[4,4,3,2,0,0],"WavePosition":"s_1_wl_0_w_1_e_1"},{"HeroId":"Korath","Power":6586,"Level":43,"GearLevel":7,"Loyalty":3,"RedStar":0,"Abilities":[4,4,3,2,0,0],"WavePosition":"s_1_wl_0_w_1_e_2"},{"HeroId":"KreeDmg_Offense","Power":6284,"Level":43,"GearLevel":7,"Loyalty":3,"RedStar":0,"Abilities":[4,4,3,2,0,0],"WavePosition":"s_1_wl_0_w_2_e_0"},{"HeroId":"KreeDmg_Offense","Power":6284,"Level":43,"GearLevel":7,"Loyalty":3,"RedStar":0,"Abilities":[4,4,3,2,0,0],"WavePosition":"s_1_wl_0_w_2_e_1"},{"HeroId":"KreeDmg_Speed","Power":6324,"Level":43,"GearLevel":7,"Loyalty":3,"RedStar":0,"Abilities":[4,4,3,2,0,0],"WavePosition":"s_1_wl_0_w_2_e_2"}]}]},{"ID":"ecm_scream_b_03","locNameKey":"ID_ECM_SCREAM_03_NAME","locDescriptionName":"ID_ECM_SCREAM_03_DESC","mapName":"Env_DestroyedCity_merged","timeOfDay":"DAY","Settings":[{"Objectives":[{"ObjectiveEndStory":"ecm_scream_03_end","CantPersist":false,"Type":"KillAll"}],"Power":6875,"TotalHealth":17893,"CompactWave":[{"HeroId":"Scream","Power":6875,"Level":44,"GearLevel":7,"Loyalty":3,"RedStar":0,"Abilities":[4,4,3,2,0,0],"WavePosition":"s_0_wl_0_w_0_e_0"}],"PresetCharacters":[{"Description":null,"Expanded":false,"Waves":[{"Expanded":true,"NextWaveIf":"AfterAllDead","TurnSpeed":1000,"MaxSlotFill":5,"MinSlotReq":0,"Entries":[{"abilities":[4,4,3,2,0,0],"useDefaultStats":false,"hero_id":"Scream","level":44,"loyalty":3,"tier":7,"desired_x_pos":4,"desired_y_pos":0}],"StoryTellingID":"ecm_scream_03_start","EmptyStoryDelay":0,"HoldSpawnStory":false}]}]},{"Power":74117,"TotalHealth":202946,"CompactWave":[{"HeroId":"Scream","Power":6775,"Level":44,"GearLevel":7,"Loyalty":3,"RedStar":0,"Abilities":[4,4,3,2,0,0],"WavePosition":"s_1_wl_0_w_0_e_0"},{"HeroId":"Scream","Power":6775,"Level":44,"GearLevel":7,"Loyalty":3,"RedStar":0,"Abilities":[4,4,3,2,0,0],"WavePosition":"s_1_wl_0_w_0_e_1"},{"HeroId":"Venom","Power":6662,"Level":44,"GearLevel":7,"Loyalty":3,"RedStar":0,"Abilities":[4,4,3,2,0,0],"WavePosition":"s_1_wl_0_w_0_e_2"},{"HeroId":"Carnage","Power":6770,"Level":44,"GearLevel":7,"Loyalty":3,"RedStar":0,"Abilities":[4,4,3,2,0,0],"WavePosition":"s_1_wl_0_w_0_e_3"},{"HeroId":"Deadpool","Power":6670,"Level":44,"GearLevel":7,"Loyalty":3,"RedStar":0,"Abilities":[4,4,3,2,0,0],"WavePosition":"s_1_wl_0_w_0_e_4"},{"HeroId":"Deadpool","Power":6670,"Level":44,"GearLevel":7,"Loyalty":3,"RedStar":0,"Abilities":[4,4,3,2,0,0],"WavePosition":"s_1_wl_0_w_0_e_5"},{"HeroId":"AntiVenom","Power":6933,"Level":44,"GearLevel":7,"Loyalty":3,"RedStar":0,"Abilities":[4,4,3,2,0,0],"WavePosition":"s_1_wl_0_w_1_e_0"},{"HeroId":"RocketRaccoon","Power":6733,"Level":44,"GearLevel":7,"Loyalty":3,"RedStar":0,"Abilities":[4,4,3,2,0,0],"WavePosition":"s_1_wl_0_w_1_e_1"},{"HeroId":"RocketRaccoon","Power":6733,"Level":44,"GearLevel":7,"Loyalty":3,"RedStar":0,"Abilities":[4,4,3,2,0,0],"WavePosition":"s_1_wl_0_w_1_e_2"},{"HeroId":"Groot","Power":6684,"Level":44,"GearLevel":7,"Loyalty":3,"RedStar":0,"Abilities":[4,4,3,2,0,0],"WavePosition":"s_1_wl_0_w_1_e_3"},{"HeroId":"Drax","Power":6712,"Level":44,"GearLevel":7,"Loyalty":3,"RedStar":0,"Abilities":[4,4,3,2,0,0],"WavePosition":"s_1_wl_0_w_1_e_4"}]}]},{"ID":"ecm_scream_b_04","locNameKey":"ID_ECM_SCREAM_04_NAME","locDescriptionName":"ID_ECM_SCREAM_04_DESC","mapName":"Env_HellsKitchen_Alleyway_merged","timeOfDay":"NIGHT","Settings":[{"Objectives":[{"ObjectiveEndStory":"ecm_scream_04_end","CantPersist":false,"Type":"KillAll"}],"Power":7589,"TotalHealth":18249,"CompactWave":[{"HeroId":"Scream","Power":7589,"Level":45,"GearLevel":7,"Loyalty":3,"RedStar":0,"Abilities":[4,4,4,2,0,0],"WavePosition":"s_0_wl_0_w_0_e_0"}],"PresetCharacters":[{"Description":null,"Expanded":false,"Waves":[{"Expanded":true,"TurnSpeed":1000,"MaxSlotFill":2,"MinSlotReq":0,"Entries":[{"abilities":[4,4,4,2,0,0],"useDefaultStats":false,"hero_id":"Scream","level":45,"loyalty":3,"tier":7,"desired_x_pos":4,"desired_y_pos":0}],"StoryTellingID":"ecm_scream_04_start","EmptyStoryDelay":0,"HoldSpawnStory":false}]}]},{"Objectives":[{"CantPersist":false,"Type":"KillAll"}],"Power":74456,"TotalHealth":178720,"CompactWave":[{"HeroId":"Crossbones","Power":7418,"Level":45,"GearLevel":7,"Loyalty":3,"RedStar":0,"Abilities":[4,4,4,2,0,0],"WavePosition":"s_1_wl_0_w_0_e_0"},{"HeroId":"Crossbones","Power":7418,"Level":45,"GearLevel":7,"Loyalty":3,"RedStar":0,"Abilities":[4,4,4,2,0,0],"WavePosition":"s_1_wl_0_w_0_e_1"},{"HeroId":"AntMan","Power":7352,"Level":45,"GearLevel":7,"Loyalty":3,"RedStar":0,"Abilities":[4,4,4,2,0,0],"WavePosition":"s_1_wl_0_w_0_e_2"},{"HeroId":"Wasp","Power":7425,"Level":45,"GearLevel":7,"Loyalty":3,"RedStar":0,"Abilities":[4,4,4,2,0,0],"WavePosition":"s_1_wl_0_w_0_e_3"},{"HeroId":"Wasp","Power":7425,"Level":45,"GearLevel":7,"Loyalty":3,"RedStar":0,"Abilities":[4,4,4,2,0,0],"WavePosition":"s_1_wl_0_w_0_e_4"},{"HeroId":"Cable","Power":7428,"Level":45,"GearLevel":7,"Loyalty":3,"RedStar":0,"Abilities":[4,4,4,2,0,0],"WavePosition":"s_1_wl_0_w_0_e_5"},{"HeroId":"Negasonic","Power":7446,"Level":45,"GearLevel":7,"Loyalty":3,"RedStar":0,"Abilities":[4,4,4,2,0,0],"WavePosition":"s_1_wl_0_w_1_e_0"},{"HeroId":"X23","Power":7634,"Level":45,"GearLevel":7,"Loyalty":3,"RedStar":0,"Abilities":[4,4,4,2,0,0],"WavePosition":"s_1_wl_0_w_1_e_1"},{"HeroId":"Domino","Power":7474,"Level":45,"GearLevel":7,"Loyalty":3,"RedStar":0,"Abilities":[4,4,4,2,0,0],"WavePosition":"s_1_wl_0_w_1_e_2"},{"HeroId":"Deadpool","Power":7436,"Level":45,"GearLevel":7,"Loyalty":3,"RedStar":0,"Abilities":[4,4,4,2,0,0],"WavePosition":"s_1_wl_0_w_1_e_3"}]}]},{"ID":"ecm_scream_b_05","locNameKey":"ID_ECM_SCREAM_05_NAME","locDescriptionName":"ID_ECM_SCREAM_05_DESC","mapName":"Env_Warehouse_merged","timeOfDay":"DAY","Settings":[{"Objectives":[{"ObjectiveEndStory":"ecm_scream_05_end","CantPersist":false,"Type":"KillAll"}],"Power":7589,"TotalHealth":18249,"CompactWave":[{"HeroId":"Scream","Power":7589,"Level":45,"GearLevel":7,"Loyalty":3,"RedStar":0,"Abilities":[4,4,4,2,0,0],"WavePosition":"s_0_wl_0_w_0_e_0"}],"PresetCharacters":[{"Description":null,"Expanded":false,"Waves":[{"Expanded":true,"TurnSpeed":1000,"MaxSlotFill":2,"MinSlotReq":0,"Entries":[{"abilities":[4,4,4,2,0,0],"useDefaultStats":false,"hero_id":"Scream","level":45,"loyalty":3,"tier":7,"desired_x_pos":4,"desired_y_pos":0}],"StoryTellingID":"ecm_scream_05_start","EmptyStoryDelay":0,"HoldSpawnStory":false}]}]},{"Objectives":[{"ObjectiveEndStory":"ecm_scream_05_end","CantPersist":false,"Type":"KillAll"}],"Power":88147,"TotalHealth":279469,"CompactWave":[{"HeroId":"InvisibleWoman","Power":7589,"Level":45,"GearLevel":7,"Loyalty":3,"RedStar":0,"Abilities":[4,4,4,2,0,0],"WavePosition":"s_1_wl_0_w_0_e_0"},{"HeroId":"MrFantastic","Power":7532,"Level":45,"GearLevel":7,"Loyalty":3,"RedStar":0,"Abilities":[4,4,4,2,0,0],"WavePosition":"s_1_wl_0_w_0_e_1"},{"HeroId":"Namor","Power":7614,"Level":45,"GearLevel":7,"Loyalty":3,"RedStar":0,"Abilities":[4,4,4,2,0,0],"WavePosition":"s_1_wl_0_w_0_e_2"},{"HeroId":"Namor","Power":7614,"Level":45,"GearLevel":7,"Loyalty":3,"RedStar":0,"Abilities":[4,4,4,2,0,0],"WavePosition":"s_1_wl_0_w_0_e_3"},{"HeroId":"ShieldSupport_Stealth","Power":6629,"Level":45,"GearLevel":7,"Loyalty":3,"RedStar":0,"Abilities":[4,4,4,2,0,0],"WavePosition":"s_1_wl_0_w_0_e_4"},{"HeroId":"ShieldSupport_Heal","Power":6609,"Level":45,"GearLevel":7,"Loyalty":3,"RedStar":0,"Abilities":[4,4,4,2,0,0],"WavePosition":"s_1_wl_0_w_0_e_5"},{"HeroId":"Thing","Power":7579,"Level":45,"GearLevel":7,"Loyalty":3,"RedStar":0,"Abilities":[4,4,4,2,0,0],"WavePosition":"s_1_wl_0_w_1_e_0"},{"HeroId":"Thing","Power":7579,"Level":45,"GearLevel":7,"Loyalty":3,"RedStar":0,"Abilities":[4,4,4,2,0,0],"WavePosition":"s_1_wl_0_w_1_e_1"},{"HeroId":"HumanTorch","Power":7607,"Level":45,"GearLevel":7,"Loyalty":3,"RedStar":0,"Abilities":[4,4,4,2,0,0],"WavePosition":"s_1_wl_0_w_1_e_2"},{"HeroId":"HumanTorch","Power":7607,"Level":45,"GearLevel":7,"Loyalty":3,"RedStar":0,"Abilities":[4,4,4,2,0,0],"WavePosition":"s_1_wl_0_w_1_e_3"},{"HeroId":"ShieldTank_Stun","Power":6574,"Level":45,"GearLevel":7,"Loyalty":3,"RedStar":0,"Abilities":[4,4,4,2,0,0],"WavePosition":"s_1_wl_0_w_1_e_4"},{"HeroId":"Namor","Power":7614,"Level":45,"GearLevel":7,"Loyalty":3,"RedStar":0,"Abilities":[4,4,4,2,0,0],"WavePosition":"s_1_wl_0_w_1_e_5"}]}]},{"ID":"ecm_scream_b_06","locNameKey":"ID_ECM_SCREAM_06_NAME","locDescriptionName":"ID_ECM_SCREAM_06_DESC","mapName":"Env_Bunker_Storage_merged","timeOfDay":"SUNSET","Settings":[{"Objectives":[{"ObjectiveEndStory":"ecm_scream_06_end","HealthPercent":25,"CantPersist":false,"Type":"WoundTarget"}],"Power":7699,"TotalHealth":18612,"CompactWave":[{"HeroId":"Scream","Power":7699,"Level":46,"GearLevel":7,"Loyalty":3,"RedStar":0,"Abilities":[4,4,4,2,0,0],"WavePosition":"s_0_wl_0_w_0_e_0"}],"PresetCharacters":[{"Description":null,"Expanded":false,"Waves":[{"Expanded":true,"TurnSpeed":1000,"MaxSlotFill":1,"MinSlotReq":0,"Entries":[{"abilities":[4,4,4,2,0,0],"useDefaultStats":false,"hero_id":"Scream","level":46,"loyalty":3,"tier":7,"desired_x_pos":4,"desired_y_pos":0}],"EmptyStoryDelay":0,"HoldSpawnStory":false}]}]},{"Objectives":[{"HealthPercent":25,"CantPersist":false,"Type":"WoundTarget"}],"Power":98166,"TotalHealth":198358,"CompactWave":[{"HeroId":"Rescue","Power":7552,"Level":46,"GearLevel":7,"Loyalty":3,"RedStar":0,"Abilities":[4,4,4,2,0,0],"WavePosition":"s_1_wl_0_w_0_e_0"},{"HeroId":"Rescue","Power":7552,"Level":46,"GearLevel":7,"Loyalty":3,"RedStar":0,"Abilities":[4,4,4,2,0,0],"WavePosition":"s_1_wl_0_w_0_e_1"},{"HeroId":"Falcon","Power":7487,"Level":46,"GearLevel":7,"Loyalty":3,"RedStar":0,"Abilities":[4,4,4,2,0,0],"WavePosition":"s_1_wl_0_w_0_e_2"},{"HeroId":"Ironheart","Power":7562,"Level":46,"GearLevel":7,"Loyalty":3,"RedStar":0,"Abilities":[4,4,4,2,0,0],"WavePosition":"s_1_wl_0_w_0_e_3"},{"HeroId":"WarMachine","Power":7477,"Level":46,"GearLevel":7,"Loyalty":3,"RedStar":0,"Abilities":[4,4,4,2,0,0],"WavePosition":"s_1_wl_0_w_0_e_4"},{"HeroId":"WarMachine","Power":7477,"Level":46,"GearLevel":7,"Loyalty":3,"RedStar":0,"Abilities":[4,4,4,2,0,0],"WavePosition":"s_1_wl_0_w_0_e_5"},{"HeroId":"CaptainAmerica","Power":7573,"Level":46,"GearLevel":7,"Loyalty":3,"RedStar":0,"Abilities":[4,4,4,2,0,0],"WavePosition":"s_1_wl_0_w_1_e_0"},{"HeroId":"Rescue","Power":7552,"Level":46,"GearLevel":7,"Loyalty":3,"RedStar":0,"Abilities":[4,4,4,2,0,0],"WavePosition":"s_1_wl_0_w_1_e_1"},{"HeroId":"Ironheart","Power":7562,"Level":46,"GearLevel":7,"Loyalty":3,"RedStar":0,"Abilities":[4,4,4,2,0,0],"WavePosition":"s_1_wl_0_w_1_e_2"},{"HeroId":"IronMan","Power":7596,"Level":46,"GearLevel":7,"Loyalty":3,"RedStar":0,"Abilities":[4,4,4,2,0,0],"WavePosition":"s_1_wl_0_w_1_e_3"},{"HeroId":"Colossus","Power":7595,"Level":46,"GearLevel":7,"Loyalty":3,"RedStar":0,"Abilities":[4,4,4,2,0,0],"WavePosition":"s_1_wl_0_w_2_e_0"},{"HeroId":"Psylocke","Power":7634,"Level":46,"GearLevel":7,"Loyalty":3,"RedStar":0,"Abilities":[4,4,4,2,0,0],"WavePosition":"s_1_wl_0_w_2_e_1"},{"HeroId":"Mantis","Power":7547,"Level":46,"GearLevel":7,"Loyalty":3,"RedStar":0,"Abilities":[4,4,4,2,0,0],"WavePosition":"s_1_wl_0_w_2_e_2"}]}]},{"ID":"ecm_scream_b_07","locNameKey":"ID_ECM_SCREAM_07_NAME","locDescriptionName":"ID_ECM_SCREAM_07_DESC","mapName":"Env_Bunker_Storage_merged","timeOfDay":"SUNSET","Settings":[{"Objectives":[{"ObjectiveEndStory":"ecm_scream_07_end","CantPersist":false,"Type":"KillAll"}],"Power":7699,"TotalHealth":18612,"CompactWave":[{"HeroId":"Scream","Power":7699,"Level":46,"GearLevel":7,"Loyalty":3,"RedStar":0,"Abilities":[4,4,4,2,0,0],"WavePosition":"s_0_wl_0_w_0_e_0"}],"PresetCharacters":[{"Description":null,"Expanded":false,"Waves":[{"Expanded":true,"TurnSpeed":1000,"MaxSlotFill":1,"MinSlotReq":0,"Entries":[{"abilities":[4,4,4,2,0,0],"useDefaultStats":false,"hero_id":"Scream","level":46,"loyalty":3,"tier":7,"desired_x_pos":4,"desired_y_pos":0}],"EmptyStoryDelay":0,"HoldSpawnStory":false}]}]},{"Objectives":[{"CantPersist":false,"Type":"KillAll"}],"Power":87722,"TotalHealth":191492,"CompactWave":[{"HeroId":"IronMan","Power":7591,"Level":46,"GearLevel":7,"Loyalty":3,"RedStar":0,"Abilities":[4,4,4,2,0,0],"WavePosition":"s_1_wl_0_w_0_e_0"},{"HeroId":"Crystal","Power":7514,"Level":46,"GearLevel":7,"Loyalty":3,"RedStar":0,"Abilities":[4,4,4,2,0,0],"WavePosition":"s_1_wl_0_w_1_e_0"},{"HeroId":"Quake","Power":7372,"Level":46,"GearLevel":7,"Loyalty":3,"RedStar":0,"Abilities":[4,4,4,2,0,0],"WavePosition":"s_1_wl_0_w_1_e_1"},{"HeroId":"Quake","Power":7372,"Level":46,"GearLevel":7,"Loyalty":3,"RedStar":0,"Abilities":[4,4,4,2,0,0],"WavePosition":"s_1_wl_0_w_1_e_2"},{"HeroId":"YoYo","Power":7567,"Level":46,"GearLevel":7,"Loyalty":3,"RedStar":0,"Abilities":[4,4,4,2,0,0],"WavePosition":"s_1_wl_0_w_1_e_3"},{"HeroId":"Yondu","Power":7429,"Level":46,"GearLevel":7,"Loyalty":3,"RedStar":0,"Abilities":[4,4,4,2,0,0],"WavePosition":"s_1_wl_0_w_1_e_4"},{"HeroId":"Karnak","Power":7713,"Level":46,"GearLevel":7,"Loyalty":3,"RedStar":0,"Abilities":[4,4,4,2,0,0],"WavePosition":"s_1_wl_0_w_2_e_0"},{"HeroId":"YoYo","Power":7647,"Level":46,"GearLevel":7,"Loyalty":3,"RedStar":0,"Abilities":[4,4,4,2,0,0],"WavePosition":"s_1_wl_0_w_2_e_1"},{"HeroId":"Crystal","Power":7585,"Level":46,"GearLevel":7,"Loyalty":3,"RedStar":0,"Abilities":[4,4,4,2,0,0],"WavePosition":"s_1_wl_0_w_2_e_2"},{"HeroId":"KreeSupport_HoT","Power":6654,"Level":46,"GearLevel":7,"Loyalty":3,"RedStar":0,"Abilities":[4,4,4,2,0,0],"WavePosition":"s_1_wl_0_w_2_e_3"},{"HeroId":"KreeDmg_Speed","Power":6639,"Level":46,"GearLevel":7,"Loyalty":3,"RedStar":0,"Abilities":[4,4,4,2,0,0],"WavePosition":"s_1_wl_0_w_2_e_4"},{"HeroId":"KreeDmg_Speed","Power":6639,"Level":46,"GearLevel":7,"Loyalty":3,"RedStar":0,"Abilities":[4,4,4,2,0,0],"WavePosition":"s_1_wl_0_w_2_e_5"}]}]},{"ID":"ecm_scream_b_08","locNameKey":"ID_ECM_SCREAM_08_NAME","locDescriptionName":"ID_ECM_SCREAM_08_DESC","mapName":"Env_Hydra_Base_merged","timeOfDay":"SUNSET","Settings":[{"Objectives":[{"ObjectiveEndStory":"ecm_scream_08_end","CantPersist":false,"Type":"KillAll"}],"Power":7810,"TotalHealth":18981,"CompactWave":[{"HeroId":"Scream","Power":7810,"Level":47,"GearLevel":7,"Loyalty":3,"RedStar":0,"Abilities":[4,4,4,2,0,0],"WavePosition":"s_0_wl_0_w_0_e_0"}],"PresetCharacters":[{"Description":null,"Expanded":false,"Waves":[{"Expanded":true,"TurnSpeed":1000,"MaxSlotFill":1,"MinSlotReq":0,"Entries":[{"abilities":[4,4,4,2,0,0],"useDefaultStats":false,"hero_id":"Scream","level":47,"loyalty":3,"tier":7,"desired_x_pos":4,"desired_y_pos":0}],"EmptyStoryDelay":0,"HoldSpawnStory":false}]}]},{"Objectives":[{"CantPersist":false,"Type":"KillAll"}],"Power":87103,"TotalHealth":253768,"CompactWave":[{"HeroId":"DoctorStrange","Power":7930,"Level":47,"GearLevel":7,"Loyalty":3,"RedStar":0,"PercentageEquippedGear":50,"Abilities":[4,4,4,2,0,0],"WavePosition":"s_1_wl_0_w_0_e_0"},{"HeroId":"GhostRider","Power":8299,"Level":47,"GearLevel":7,"Loyalty":3,"RedStar":0,"PercentageEquippedGear":50,"Abilities":[4,4,4,2,0,0],"WavePosition":"s_1_wl_0_w_0_e_1"},{"HeroId":"BaronMordo","Power":8007,"Level":47,"GearLevel":7,"Loyalty":3,"RedStar":0,"PercentageEquippedGear":50,"Abilities":[4,4,4,2,0,0],"WavePosition":"s_1_wl_0_w_0_e_2"},{"HeroId":"ElsaBloodstone","Power":8134,"Level":47,"GearLevel":7,"Loyalty":3,"RedStar":0,"PercentageEquippedGear":50,"Abilities":[4,4,4,2,0,0],"WavePosition":"s_1_wl_0_w_0_e_3"},{"HeroId":"ElsaBloodstone","Power":8134,"Level":47,"GearLevel":7,"Loyalty":3,"RedStar":0,"PercentageEquippedGear":50,"Abilities":[4,4,4,2,0,0],"WavePosition":"s_1_wl_0_w_0_e_4"},{"HeroId":"Drax","Power":7975,"Level":47,"GearLevel":7,"Loyalty":3,"RedStar":0,"PercentageEquippedGear":50,"Abilities":[4,4,4,2,0,0],"WavePosition":"s_1_wl_0_w_0_e_5"},{"HeroId":"ScarletWitch","Power":7566,"Level":46,"GearLevel":7,"Loyalty":3,"RedStar":0,"Abilities":[4,4,4,2,0,0],"WavePosition":"s_1_wl_0_w_1_e_0"},{"HeroId":"ElsaBloodstone","Power":7667,"Level":46,"GearLevel":7,"Loyalty":3,"RedStar":0,"Abilities":[4,4,4,2,0,0],"WavePosition":"s_1_wl_0_w_1_e_1"},{"HeroId":"Thing","Power":8078,"Level":46,"GearLevel":7,"Loyalty":3,"RedStar":0,"PercentageEquippedGear":50,"Abilities":[4,4,4,2,0,0],"WavePosition":"s_1_wl_0_w_1_e_2"},{"HeroId":"MrSinister","Power":7767,"Level":46,"GearLevel":7,"Loyalty":3,"RedStar":0,"Abilities":[4,4,4,2,0,0],"WavePosition":"s_1_wl_0_w_2_e_0"},{"HeroId":"BaronMordo","Power":7546,"Level":46,"GearLevel":7,"Loyalty":3,"RedStar":0,"Abilities":[4,4,4,2,0,0],"WavePosition":"s_1_wl_0_w_2_e_1"}]}]},{"ID":"ecm_scream_b_09","locNameKey":"ID_ECM_SCREAM_09_NAME","locDescriptionName":"ID_ECM_SCREAM_09_DESC","mapName":"Env_Hydra_Base_merged","timeOfDay":"SUNSET","Settings":[{"Objectives":[{"ObjectiveEndStory":"ecm_scream_09_end","CantPersist":false,"Type":"KillAll"}],"Power":8226,"TotalHealth":20234,"CompactWave":[{"HeroId":"Scream","Power":8226,"Level":48,"GearLevel":7,"Loyalty":3,"RedStar":0,"Abilities":[4,4,4,3,0,0],"WavePosition":"s_0_wl_0_w_0_e_0"}],"PresetCharacters":[{"Description":null,"Expanded":false,"Waves":[{"Expanded":true,"TurnSpeed":1000,"MaxSlotFill":1,"MinSlotReq":0,"Entries":[{"abilities":[4,4,4,3,0,0],"useDefaultStats":false,"hero_id":"Scream","level":48,"loyalty":3,"tier":7,"desired_x_pos":4,"desired_y_pos":0}],"EmptyStoryDelay":0,"HoldSpawnStory":false}]}]},{"Objectives":[{"CantPersist":false,"Type":"KillAll"}],"Power":60924,"TotalHealth":122594,"CompactWave":[{"HeroId":"BlackBolt","Power":8184,"Level":48,"GearLevel":7,"Loyalty":3,"RedStar":0,"Abilities":[4,4,4,3,0,0],"WavePosition":"s_1_wl_0_w_0_e_0"},{"HeroId":"WarMachine","Power":7953,"Level":48,"GearLevel":7,"Loyalty":3,"RedStar":0,"Abilities":[4,4,4,3,0,0],"WavePosition":"s_1_wl_0_w_0_e_1"},{"HeroId":"Magneto","Power":8041,"Level":48,"GearLevel":7,"Loyalty":3,"RedStar":0,"Abilities":[4,4,4,3,0,0],"WavePosition":"s_1_wl_0_w_0_e_2"},{"HeroId":"Quake","Power":7867,"Level":48,"GearLevel":7,"Loyalty":3,"RedStar":0,"Abilities":[4,4,4,3,0,0],"WavePosition":"s_1_wl_0_w_0_e_3"},{"HeroId":"Crystal","Power":8025,"Level":48,"GearLevel":7,"Loyalty":3,"RedStar":0,"Abilities":[4,4,4,3,0,0],"WavePosition":"s_1_wl_0_w_0_e_4"},{"HeroId":"Minerva","Power":6901,"Level":48,"GearLevel":6,"Loyalty":3,"RedStar":0,"Abilities":[4,4,4,3,0,0],"WavePosition":"s_1_wl_0_w_1_e_0"},{"HeroId":"Phoenix","Power":6967,"Level":48,"GearLevel":6,"Loyalty":3,"RedStar":0,"Abilities":[4,4,4,3,0,0],"WavePosition":"s_1_wl_0_w_1_e_1"},{"HeroId":"YoYo","Power":6986,"Level":48,"GearLevel":6,"Loyalty":3,"RedStar":0,"Abilities":[4,4,4,3,0,0],"WavePosition":"s_1_wl_0_w_1_e_2"}]}]},{"ID":"ecm_scream_c_01","locNameKey":"ID_ECM_SCREAM_01_NAME","locDescriptionName":"ID_ECM_SCREAM_01_DESC","mapName":"Env_Jungle_merged","timeOfDay":"SUNSET","Settings":[{"Objectives":[{"ObjectiveEndStory":"ecm_scream_01_end","HealthPercent":25,"CantPersist":false,"Type":"WoundTarget"}],"Power":57479,"TotalHealth":131181,"CompactWave":[{"HeroId":"Scream","Power":19332,"Level":65,"GearLevel":9,"Loyalty":5,"RedStar":0,"Abilities":[6,5,5,4,0,0],"WavePosition":"s_0_wl_0_w_0_e_0"},{"HeroId":"Scream","Power":19157,"Level":65,"GearLevel":9,"Loyalty":5,"RedStar":0,"Abilities":[6,5,5,4,0,0],"WavePosition":"s_0_wl_0_w_1_e_0"},{"HeroId":"Scream","Power":18990,"Level":65,"GearLevel":9,"Loyalty":5,"RedStar":0,"Abilities":[6,5,5,4,0,0],"WavePosition":"s_0_wl_0_w_1_e_1"}],"PresetCharacters":[{"Description":null,"Expanded":false,"Waves":[{"Expanded":true,"InitialTurnFill":500,"TurnSpeed":1000,"MaxSlotFill":1,"MinSlotReq":0,"Entries":[{"abilities":[6,5,5,4,0,0],"useDefaultStats":false,"hero_id":"Scream","level":65,"loyalty":5,"tier":9,"desired_x_pos":1,"desired_y_pos":1,"stats_mod":{"crit_chance_pct":1}}],"StoryTellingID":"ecm_scream_01_start","EmptyStoryDelay":0,"HoldSpawnStory":true},{"Expanded":true,"TurnSpeed":1000,"MaxSlotFill":2,"MinSlotReq":0,"Entries":[{"abilities":[6,5,5,4,0,0],"useDefaultStats":false,"hero_id":"Scream","level":65,"loyalty":5,"tier":9,"desired_x_pos":2,"desired_y_pos":0,"stats_mod":{"speed":85}},{"abilities":[6,5,5,4,0,0],"useDefaultStats":false,"hero_id":"Scream","level":65,"loyalty":5,"tier":9,"desired_x_pos":0,"desired_y_pos":0,"stats_mod":{"speed":75}}],"EmptyStoryDelay":0,"HoldSpawnStory":false}]}]},{"Objectives":[{"CantPersist":false,"Type":"KillAll"}],"Power":60360,"TotalHealth":175888,"CompactWave":[{"HeroId":"Shocker","Power":9461,"Level":55,"GearLevel":6,"Loyalty":4,"RedStar":0,"Abilities":[5,5,4,3,0,0],"WavePosition":"s_1_wl_0_w_0_e_0"},{"HeroId":"UltSpiderMan","Power":8843,"Level":55,"GearLevel":6,"Loyalty":4,"RedStar":0,"Abilities":[5,5,4,1,0,0],"WavePosition":"s_1_wl_0_w_1_e_0"},{"HeroId":"UltSpiderMan","Power":8856,"Level":55,"GearLevel":6,"Loyalty":4,"RedStar":0,"Abilities":[5,5,4,1,0,0],"WavePosition":"s_1_wl_0_w_1_e_1"},{"HeroId":"Venom","Power":15110,"Level":60,"GearLevel":8,"Loyalty":5,"RedStar":0,"Abilities":[5,5,5,4,0,0],"WavePosition":"s_1_wl_0_w_2_e_0"},{"HeroId":"Carnage","Power":8603,"Level":55,"GearLevel":5,"Loyalty":4,"RedStar":0,"Abilities":[5,5,4,3,0,0],"WavePosition":"s_1_wl_0_w_2_e_1"},{"HeroId":"UltSpiderMan","Power":9487,"Level":55,"GearLevel":6,"Loyalty":4,"RedStar":0,"Abilities":[5,5,4,3,0,0],"WavePosition":"s_1_wl_0_w_2_e_2"}]}]},{"ID":"ecm_scream_c_02","locNameKey":"ID_ECM_SCREAM_02_NAME","locDescriptionName":"ID_ECM_SCREAM_02_DESC","mapName":"Env_Kree_Bridge_merged","timeOfDay":"NIGHT","Settings":[{"Objectives":[{"ObjectiveEndStory":"ecm_scream_02_end","CantPersist":false,"Type":"KillAll"}],"Power":1793,"TotalHealth":5186,"CompactWave":[{"HeroId":"Scream","Power":1793,"Level":27,"GearLevel":4,"Loyalty":2,"RedStar":0,"Abilities":[3,2,2,1,0,0],"WavePosition":"s_0_wl_0_w_0_e_0"}],"PresetCharacters":[{"Description":null,"Expanded":false,"Waves":[{"Expanded":true,"TurnSpeed":1000,"MaxSlotFill":5,"MinSlotReq":0,"Entries":[{"abilities":[3,2,2,1,0,0],"useDefaultStats":false,"hero_id":"Scream","level":27,"loyalty":2,"tier":4,"desired_x_pos":4,"desired_y_pos":0}],"StoryTellingID":"ecm_scream_02_start","EmptyStoryDelay":0,"HoldSpawnStory":false}]}]},{"Objectives":[{"CantPersist":false,"Type":"KillAll"}],"Power":14361,"TotalHealth":54865,"CompactWave":[{"HeroId":"KreeControl_Assist","Power":1542,"Level":27,"GearLevel":4,"Loyalty":2,"RedStar":0,"Abilities":[3,2,2,1,0,0],"WavePosition":"s_1_wl_0_w_0_e_0"},{"HeroId":"KreeControl_Assist","Power":1542,"Level":27,"GearLevel":4,"Loyalty":2,"RedStar":0,"Abilities":[3,2,2,1,0,0],"WavePosition":"s_1_wl_0_w_0_e_1"},{"HeroId":"Ronan","Power":1774,"Level":27,"GearLevel":4,"Loyalty":2,"RedStar":0,"Abilities":[3,2,2,1,0,0],"WavePosition":"s_1_wl_0_w_0_e_2"},{"HeroId":"KreeDmg_Speed","Power":1543,"Level":27,"GearLevel":4,"Loyalty":2,"RedStar":0,"Abilities":[3,2,2,1,0,0],"WavePosition":"s_1_wl_0_w_0_e_3"},{"HeroId":"KreeDmg_Speed","Power":1543,"Level":27,"GearLevel":4,"Loyalty":2,"RedStar":0,"Abilities":[3,2,2,1,0,0],"WavePosition":"s_1_wl_0_w_0_e_4"},{"HeroId":"KreeTank_Counter","Power":1573,"Level":27,"GearLevel":4,"Loyalty":2,"RedStar":0,"Abilities":[3,2,2,1,0,0],"WavePosition":"s_1_wl_0_w_1_e_0"},{"HeroId":"Korath","Power":1767,"Level":27,"GearLevel":4,"Loyalty":2,"RedStar":0,"Abilities":[3,2,2,1,0,0],"WavePosition":"s_1_wl_0_w_1_e_1"},{"HeroId":"KreeDmg_Offense","Power":1534,"Level":27,"GearLevel":4,"Loyalty":2,"RedStar":0,"Abilities":[3,2,2,1,0,0],"WavePosition":"s_1_wl_0_w_2_e_0"},{"HeroId":"KreeDmg_Speed","Power":1543,"Level":27,"GearLevel":4,"Loyalty":2,"RedStar":0,"Abilities":[3,2,2,1,0,0],"WavePosition":"s_1_wl_0_w_2_e_1"}]}]},{"ID":"ecm_scream_c_03","locNameKey":"ID_ECM_SCREAM_03_NAME","locDescriptionName":"ID_ECM_SCREAM_03_DESC","mapName":"Env_DestroyedCity_merged","timeOfDay":"DAY","Settings":[{"Objectives":[{"ObjectiveEndStory":"ecm_scream_03_end","CantPersist":false,"Type":"KillAll"}],"Power":1838,"TotalHealth":5343,"CompactWave":[{"HeroId":"Scream","Power":1838,"Level":28,"GearLevel":4,"Loyalty":2,"RedStar":0,"Abilities":[3,2,2,1,0,0],"WavePosition":"s_0_wl_0_w_0_e_0"}],"PresetCharacters":[{"Description":null,"Expanded":false,"Waves":[{"Expanded":true,"NextWaveIf":"AfterAllDead","TurnSpeed":1000,"MaxSlotFill":5,"MinSlotReq":0,"Entries":[{"abilities":[3,2,2,1,0,0],"useDefaultStats":false,"hero_id":"Scream","level":28,"loyalty":2,"tier":4,"desired_x_pos":4,"desired_y_pos":0}],"StoryTellingID":"ecm_scream_03_start","EmptyStoryDelay":0,"HoldSpawnStory":false}]}]},{"Power":14503,"TotalHealth":52910,"CompactWave":[{"HeroId":"Scream","Power":1838,"Level":28,"GearLevel":4,"Loyalty":2,"RedStar":0,"Abilities":[3,2,2,1,0,0],"WavePosition":"s_1_wl_0_w_0_e_0"},{"HeroId":"Venom","Power":1801,"Level":28,"GearLevel":4,"Loyalty":2,"RedStar":0,"Abilities":[3,2,2,1,0,0],"WavePosition":"s_1_wl_0_w_0_e_1"},{"HeroId":"Carnage","Power":1833,"Level":28,"GearLevel":4,"Loyalty":2,"RedStar":0,"Abilities":[3,2,2,1,0,0],"WavePosition":"s_1_wl_0_w_0_e_2"},{"HeroId":"Deadpool","Power":1808,"Level":28,"GearLevel":4,"Loyalty":2,"RedStar":0,"Abilities":[3,2,2,1,0,0],"WavePosition":"s_1_wl_0_w_0_e_3"},{"HeroId":"AntiVenom","Power":1844,"Level":28,"GearLevel":4,"Loyalty":2,"RedStar":0,"Abilities":[3,2,2,1,0,0],"WavePosition":"s_1_wl_0_w_1_e_0"},{"HeroId":"RocketRaccoon","Power":1805,"Level":28,"GearLevel":4,"Loyalty":2,"RedStar":0,"Abilities":[3,2,2,1,0,0],"WavePosition":"s_1_wl_0_w_1_e_1"},{"HeroId":"Groot","Power":1785,"Level":28,"GearLevel":4,"Loyalty":2,"RedStar":0,"Abilities":[3,2,2,1,0,0],"WavePosition":"s_1_wl_0_w_1_e_2"},{"HeroId":"Drax","Power":1789,"Level":28,"GearLevel":4,"Loyalty":2,"RedStar":0,"Abilities":[3,2,2,1,0,0],"WavePosition":"s_1_wl_0_w_1_e_3"}]}]},{"ID":"ecm_scream_c_04","locNameKey":"ID_ECM_SCREAM_04_NAME","locDescriptionName":"ID_ECM_SCREAM_04_DESC","mapName":"Env_HellsKitchen_Alleyway_merged","timeOfDay":"NIGHT","Settings":[{"Objectives":[{"ObjectiveEndStory":"ecm_scream_04_end","CantPersist":false,"Type":"KillAll"}],"Power":1838,"TotalHealth":5343,"CompactWave":[{"HeroId":"Scream","Power":1838,"Level":28,"GearLevel":4,"Loyalty":2,"RedStar":0,"Abilities":[3,2,2,1,0,0],"WavePosition":"s_0_wl_0_w_0_e_0"}],"PresetCharacters":[{"Description":null,"Expanded":false,"Waves":[{"Expanded":true,"TurnSpeed":1000,"MaxSlotFill":2,"MinSlotReq":0,"Entries":[{"abilities":[3,2,2,1,0,0],"useDefaultStats":false,"hero_id":"Scream","level":28,"loyalty":2,"tier":4,"desired_x_pos":4,"desired_y_pos":0}],"StoryTellingID":"ecm_scream_04_start","EmptyStoryDelay":0,"HoldSpawnStory":false}]}]},{"Objectives":[{"CantPersist":false,"Type":"KillAll"}],"Power":14448,"TotalHealth":44709,"CompactWave":[{"HeroId":"Crossbones","Power":1795,"Level":28,"GearLevel":4,"Loyalty":2,"RedStar":0,"Abilities":[3,2,2,1,0,0],"WavePosition":"s_1_wl_0_w_0_e_0"},{"HeroId":"Crossbones","Power":1795,"Level":28,"GearLevel":4,"Loyalty":2,"RedStar":0,"Abilities":[3,2,2,1,0,0],"WavePosition":"s_1_wl_0_w_0_e_1"},{"HeroId":"AntMan","Power":1783,"Level":28,"GearLevel":4,"Loyalty":2,"RedStar":0,"Abilities":[3,2,2,1,0,0],"WavePosition":"s_1_wl_0_w_0_e_2"},{"HeroId":"Cable","Power":1799,"Level":28,"GearLevel":4,"Loyalty":2,"RedStar":0,"Abilities":[3,2,2,1,0,0],"WavePosition":"s_1_wl_0_w_0_e_3"},{"HeroId":"Negasonic","Power":1807,"Level":28,"GearLevel":4,"Loyalty":2,"RedStar":0,"Abilities":[3,2,2,1,0,0],"WavePosition":"s_1_wl_0_w_1_e_0"},{"HeroId":"X23","Power":1845,"Level":28,"GearLevel":4,"Loyalty":2,"RedStar":0,"Abilities":[3,2,2,1,0,0],"WavePosition":"s_1_wl_0_w_1_e_1"},{"HeroId":"Domino","Power":1816,"Level":28,"GearLevel":4,"Loyalty":2,"RedStar":0,"Abilities":[3,2,2,1,0,0],"WavePosition":"s_1_wl_0_w_1_e_2"},{"HeroId":"Deadpool","Power":1808,"Level":28,"GearLevel":4,"Loyalty":2,"RedStar":0,"Abilities":[3,2,2,1,0,0],"WavePosition":"s_1_wl_0_w_1_e_3"}]}]},{"ID":"ecm_scream_c_05","locNameKey":"ID_ECM_SCREAM_05_NAME","locDescriptionName":"ID_ECM_SCREAM_05_DESC","mapName":"Env_Warehouse_merged","timeOfDay":"DAY","Settings":[{"Objectives":[{"ObjectiveEndStory":"ecm_scream_05_end","CantPersist":false,"Type":"KillAll"}],"Power":2336,"TotalHealth":7043,"CompactWave":[{"HeroId":"Scream","Power":2336,"Level":29,"GearLevel":5,"Loyalty":2,"RedStar":0,"Abilities":[3,2,2,1,0,0],"WavePosition":"s_0_wl_0_w_0_e_0"}],"PresetCharacters":[{"Description":null,"Expanded":false,"Waves":[{"Expanded":true,"TurnSpeed":1000,"MaxSlotFill":2,"MinSlotReq":0,"Entries":[{"abilities":[3,2,2,1,0,0],"useDefaultStats":false,"hero_id":"Scream","level":29,"loyalty":2,"tier":5,"desired_x_pos":4,"desired_y_pos":0}],"StoryTellingID":"ecm_scream_05_start","EmptyStoryDelay":0,"HoldSpawnStory":false}]}]},{"Objectives":[{"ObjectiveEndStory":"ecm_scream_05_end","CantPersist":false,"Type":"KillAll"}],"Power":22678,"TotalHealth":95316,"CompactWave":[{"HeroId":"InvisibleWoman","Power":2339,"Level":29,"GearLevel":5,"Loyalty":2,"RedStar":0,"Abilities":[3,2,2,1,0,0],"WavePosition":"s_1_wl_0_w_0_e_0"},{"HeroId":"MrFantastic","Power":2313,"Level":29,"GearLevel":5,"Loyalty":2,"RedStar":0,"Abilities":[3,2,2,1,0,0],"WavePosition":"s_1_wl_0_w_0_e_1"},{"HeroId":"Namor","Power":2332,"Level":29,"GearLevel":5,"Loyalty":2,"RedStar":0,"Abilities":[3,2,2,1,0,0],"WavePosition":"s_1_wl_0_w_0_e_2"},{"HeroId":"Namor","Power":2332,"Level":29,"GearLevel":5,"Loyalty":2,"RedStar":0,"Abilities":[3,2,2,1,0,0],"WavePosition":"s_1_wl_0_w_0_e_3"},{"HeroId":"ShieldSupport_Heal","Power":2019,"Level":29,"GearLevel":5,"Loyalty":2,"RedStar":0,"Abilities":[3,2,2,1,0,0],"WavePosition":"s_1_wl_0_w_0_e_4"},{"HeroId":"Thing","Power":2325,"Level":29,"GearLevel":5,"Loyalty":2,"RedStar":0,"Abilities":[3,2,2,1,0,0],"WavePosition":"s_1_wl_0_w_1_e_0"},{"HeroId":"Thing","Power":2325,"Level":29,"GearLevel":5,"Loyalty":2,"RedStar":0,"Abilities":[3,2,2,1,0,0],"WavePosition":"s_1_wl_0_w_1_e_1"},{"HeroId":"HumanTorch","Power":2353,"Level":29,"GearLevel":5,"Loyalty":2,"RedStar":0,"Abilities":[3,2,2,1,0,0],"WavePosition":"s_1_wl_0_w_1_e_2"},{"HeroId":"ShieldTank_Stun","Power":2008,"Level":29,"GearLevel":5,"Loyalty":2,"RedStar":0,"Abilities":[3,2,2,1,0,0],"WavePosition":"s_1_wl_0_w_1_e_3"},{"HeroId":"Namor","Power":2332,"Level":29,"GearLevel":5,"Loyalty":2,"RedStar":0,"Abilities":[3,2,2,1,0,0],"WavePosition":"s_1_wl_0_w_1_e_4"}]}]},{"ID":"ecm_scream_c_06","locNameKey":"ID_ECM_SCREAM_06_NAME","locDescriptionName":"ID_ECM_SCREAM_06_DESC","mapName":"Env_Bunker_Storage_merged","timeOfDay":"SUNSET","Settings":[{"Objectives":[{"ObjectiveEndStory":"ecm_scream_06_end","HealthPercent":25,"CantPersist":false,"Type":"WoundTarget"}],"Power":2388,"TotalHealth":7626,"CompactWave":[{"HeroId":"Scream","Power":2388,"Level":30,"GearLevel":5,"Loyalty":2,"RedStar":0,"Abilities":[3,2,2,1,0,0],"WavePosition":"s_0_wl_0_w_0_e_0"}],"PresetCharacters":[{"Description":null,"Expanded":false,"Waves":[{"Expanded":true,"TurnSpeed":1000,"MaxSlotFill":1,"MinSlotReq":0,"Entries":[{"abilities":[3,2,2,1,0,0],"useDefaultStats":false,"hero_id":"Scream","level":30,"loyalty":2,"tier":5,"desired_x_pos":4,"desired_y_pos":0}],"EmptyStoryDelay":0,"HoldSpawnStory":false}]}]},{"Objectives":[{"HealthPercent":25,"CantPersist":false,"Type":"WoundTarget"}],"Power":19338,"TotalHealth":47775,"CompactWave":[{"HeroId":"Rescue","Power":2380,"Level":30,"GearLevel":5,"Loyalty":2,"RedStar":0,"Abilities":[3,2,2,1,0,0],"WavePosition":"s_1_wl_0_w_0_e_0"},{"HeroId":"Falcon","Power":2326,"Level":30,"GearLevel":5,"Loyalty":2,"RedStar":0,"Abilities":[3,2,2,1,0,0],"WavePosition":"s_1_wl_0_w_0_e_1"},{"HeroId":"Ironheart","Power":2347,"Level":30,"GearLevel":5,"Loyalty":2,"RedStar":0,"Abilities":[3,2,2,1,0,0],"WavePosition":"s_1_wl_0_w_0_e_2"},{"HeroId":"WarMachine","Power":2328,"Level":30,"GearLevel":5,"Loyalty":2,"RedStar":0,"Abilities":[3,2,2,1,0,0],"WavePosition":"s_1_wl_0_w_0_e_3"},{"HeroId":"Rescue","Power":2342,"Level":30,"GearLevel":5,"Loyalty":2,"RedStar":0,"Abilities":[3,2,2,1,0,0],"WavePosition":"s_1_wl_0_w_1_e_0"},{"HeroId":"Ironheart","Power":2333,"Level":30,"GearLevel":5,"Loyalty":2,"RedStar":0,"Abilities":[3,2,2,1,0,0],"WavePosition":"s_1_wl_0_w_1_e_1"},{"HeroId":"IronMan","Power":2373,"Level":30,"GearLevel":5,"Loyalty":2,"RedStar":0,"Abilities":[3,2,2,1,0,0],"WavePosition":"s_1_wl_0_w_1_e_2"},{"HeroId":"Colossus","Power":1458,"Level":28,"GearLevel":3,"Loyalty":2,"RedStar":0,"Abilities":[3,2,2,1,0,0],"WavePosition":"s_1_wl_0_w_2_e_0"},{"HeroId":"Mantis","Power":1451,"Level":28,"GearLevel":3,"Loyalty":2,"RedStar":0,"Abilities":[3,2,2,1,0,0],"WavePosition":"s_1_wl_0_w_2_e_1"}]}]},{"ID":"ecm_scream_c_07","locNameKey":"ID_ECM_SCREAM_07_NAME","locDescriptionName":"ID_ECM_SCREAM_07_DESC","mapName":"Env_Bunker_Storage_merged","timeOfDay":"SUNSET","Settings":[{"Objectives":[{"ObjectiveEndStory":"ecm_scream_07_end","CantPersist":false,"Type":"KillAll"}],"Power":2687,"TotalHealth":7809,"CompactWave":[{"HeroId":"Scream","Power":2687,"Level":31,"GearLevel":5,"Loyalty":2,"RedStar":0,"Abilities":[3,3,2,1,0,0],"WavePosition":"s_0_wl_0_w_0_e_0"}],"PresetCharacters":[{"Description":null,"Expanded":false,"Waves":[{"Expanded":true,"TurnSpeed":1000,"MaxSlotFill":1,"MinSlotReq":0,"Entries":[{"abilities":[3,3,2,1,0,0],"useDefaultStats":false,"hero_id":"Scream","level":31,"loyalty":2,"tier":5,"desired_x_pos":4,"desired_y_pos":0}],"EmptyStoryDelay":0,"HoldSpawnStory":false}]}]},{"Objectives":[{"CantPersist":false,"Type":"KillAll"}],"Power":26291,"TotalHealth":72064,"CompactWave":[{"HeroId":"IronMan","Power":2690,"Level":31,"GearLevel":5,"Loyalty":2,"RedStar":0,"Abilities":[3,3,2,1,0,0],"WavePosition":"s_1_wl_0_w_0_e_0"},{"HeroId":"Crystal","Power":2673,"Level":31,"GearLevel":5,"Loyalty":2,"RedStar":0,"Abilities":[3,3,2,1,0,0],"WavePosition":"s_1_wl_0_w_1_e_0"},{"HeroId":"Quake","Power":2616,"Level":31,"GearLevel":5,"Loyalty":2,"RedStar":0,"Abilities":[3,3,2,1,0,0],"WavePosition":"s_1_wl_0_w_1_e_1"},{"HeroId":"YoYo","Power":2692,"Level":31,"GearLevel":5,"Loyalty":2,"RedStar":0,"Abilities":[3,3,2,1,0,0],"WavePosition":"s_1_wl_0_w_1_e_2"},{"HeroId":"Yondu","Power":2640,"Level":31,"GearLevel":5,"Loyalty":2,"RedStar":0,"Abilities":[3,3,2,1,0,0],"WavePosition":"s_1_wl_0_w_1_e_3"},{"HeroId":"Karnak","Power":2686,"Level":31,"GearLevel":5,"Loyalty":2,"RedStar":0,"Abilities":[3,3,2,1,0,0],"WavePosition":"s_1_wl_0_w_2_e_0"},{"HeroId":"YoYo","Power":2654,"Level":31,"GearLevel":5,"Loyalty":2,"RedStar":0,"Abilities":[3,3,2,1,0,0],"WavePosition":"s_1_wl_0_w_2_e_1"},{"HeroId":"Crystal","Power":2638,"Level":31,"GearLevel":5,"Loyalty":2,"RedStar":0,"Abilities":[3,3,2,1,0,0],"WavePosition":"s_1_wl_0_w_2_e_2"},{"HeroId":"KreeSupport_HoT","Power":2503,"Level":31,"GearLevel":5,"Loyalty":2,"RedStar":0,"Abilities":[3,3,2,1,0,0],"WavePosition":"s_1_wl_0_w_2_e_3"},{"HeroId":"KreeDmg_Speed","Power":2499,"Level":31,"GearLevel":5,"Loyalty":2,"RedStar":0,"Abilities":[3,3,2,1,0,0],"WavePosition":"s_1_wl_0_w_2_e_4"}]}]},{"ID":"ecm_scream_c_08","locNameKey":"ID_ECM_SCREAM_08_NAME","locDescriptionName":"ID_ECM_SCREAM_08_DESC","mapName":"Env_Hydra_Base_merged","timeOfDay":"SUNSET","Settings":[{"Objectives":[{"ObjectiveEndStory":"ecm_scream_08_end","CantPersist":false,"Type":"KillAll"}],"Power":2740,"TotalHealth":7996,"CompactWave":[{"HeroId":"Scream","Power":2740,"Level":32,"GearLevel":5,"Loyalty":2,"RedStar":0,"Abilities":[3,3,2,1,0,0],"WavePosition":"s_0_wl_0_w_0_e_0"}],"PresetCharacters":[{"Description":null,"Expanded":false,"Waves":[{"Expanded":true,"TurnSpeed":1000,"MaxSlotFill":1,"MinSlotReq":0,"Entries":[{"abilities":[3,3,2,1,0,0],"useDefaultStats":false,"hero_id":"Scream","level":32,"loyalty":2,"tier":5,"desired_x_pos":4,"desired_y_pos":0}],"EmptyStoryDelay":0,"HoldSpawnStory":false}]}]},{"Objectives":[{"CantPersist":false,"Type":"KillAll"}],"Power":21591,"TotalHealth":74403,"CompactWave":[{"HeroId":"DoctorStrange","Power":2650,"Level":32,"GearLevel":5,"Loyalty":2,"RedStar":0,"Abilities":[3,3,2,1,0,0],"WavePosition":"s_1_wl_0_w_0_e_0"},{"HeroId":"GhostRider","Power":2756,"Level":32,"GearLevel":5,"Loyalty":2,"RedStar":0,"Abilities":[3,3,2,1,0,0],"WavePosition":"s_1_wl_0_w_0_e_1"},{"HeroId":"BaronMordo","Power":2668,"Level":32,"GearLevel":5,"Loyalty":2,"RedStar":0,"Abilities":[3,3,2,1,0,0],"WavePosition":"s_1_wl_0_w_0_e_2"},{"HeroId":"ElsaBloodstone","Power":2706,"Level":32,"GearLevel":5,"Loyalty":2,"RedStar":0,"Abilities":[3,3,2,1,0,0],"WavePosition":"s_1_wl_0_w_0_e_3"},{"HeroId":"Drax","Power":2655,"Level":32,"GearLevel":5,"Loyalty":2,"RedStar":0,"Abilities":[3,3,2,1,0,0],"WavePosition":"s_1_wl_0_w_0_e_4"},{"HeroId":"ScarletWitch","Power":2700,"Level":32,"GearLevel":5,"Loyalty":2,"RedStar":0,"Abilities":[3,3,2,1,0,0],"WavePosition":"s_1_wl_0_w_1_e_0"},{"HeroId":"ElsaBloodstone","Power":2727,"Level":32,"GearLevel":5,"Loyalty":2,"RedStar":0,"Abilities":[3,3,2,1,0,0],"WavePosition":"s_1_wl_0_w_1_e_1"},{"HeroId":"Thing","Power":2729,"Level":32,"GearLevel":5,"Loyalty":2,"RedStar":0,"Abilities":[3,3,2,1,0,0],"WavePosition":"s_1_wl_0_w_1_e_2"}]}]},{"ID":"ecm_scream_c_09","locNameKey":"ID_ECM_SCREAM_09_NAME","locDescriptionName":"ID_ECM_SCREAM_09_DESC","mapName":"Env_Hydra_Base_merged","timeOfDay":"SUNSET","Settings":[{"Objectives":[{"ObjectiveEndStory":"ecm_scream_09_end","CantPersist":false,"Type":"KillAll"}],"Power":2795,"TotalHealth":8186,"CompactWave":[{"HeroId":"Scream","Power":2795,"Level":33,"GearLevel":5,"Loyalty":2,"RedStar":0,"Abilities":[3,3,2,1,0,0],"WavePosition":"s_0_wl_0_w_0_e_0"}],"PresetCharacters":[{"Description":null,"Expanded":false,"Waves":[{"Expanded":true,"TurnSpeed":1000,"MaxSlotFill":1,"MinSlotReq":0,"Entries":[{"abilities":[3,3,2,1,0,0],"useDefaultStats":false,"hero_id":"Scream","level":33,"loyalty":2,"tier":5,"desired_x_pos":4,"desired_y_pos":0}],"EmptyStoryDelay":0,"HoldSpawnStory":false}]}]},{"Objectives":[{"CantPersist":false,"Type":"KillAll"}],"Power":20090,"TotalHealth":44515,"CompactWave":[{"HeroId":"BlackBolt","Power":2282,"Level":33,"GearLevel":4,"Loyalty":2,"RedStar":0,"Abilities":[3,3,2,1,0,0],"WavePosition":"s_1_wl_0_w_0_e_0"},{"HeroId":"WarMachine","Power":2222,"Level":33,"GearLevel":4,"Loyalty":2,"RedStar":0,"Abilities":[3,3,2,1,0,0],"WavePosition":"s_1_wl_0_w_0_e_1"},{"HeroId":"Minerva","Power":2224,"Level":33,"GearLevel":4,"Loyalty":2,"RedStar":0,"Abilities":[3,3,2,1,0,0],"WavePosition":"s_1_wl_0_w_0_e_2"},{"HeroId":"Quake","Power":2198,"Level":33,"GearLevel":4,"Loyalty":2,"RedStar":0,"Abilities":[3,3,2,1,0,0],"WavePosition":"s_1_wl_0_w_0_e_3"},{"HeroId":"Quake","Power":2198,"Level":33,"GearLevel":4,"Loyalty":2,"RedStar":0,"Abilities":[3,3,2,1,0,0],"WavePosition":"s_1_wl_0_w_0_e_4"},{"HeroId":"Crystal","Power":2237,"Level":33,"GearLevel":4,"Loyalty":2,"RedStar":0,"Abilities":[3,3,2,1,0,0],"WavePosition":"s_1_wl_0_w_0_e_5"},{"HeroId":"Minerva","Power":2224,"Level":33,"GearLevel":4,"Loyalty":2,"RedStar":0,"Abilities":[3,3,2,1,0,0],"WavePosition":"s_1_wl_0_w_1_e_0"},{"HeroId":"Phoenix","Power":2257,"Level":33,"GearLevel":4,"Loyalty":2,"RedStar":0,"Abilities":[3,3,2,1,0,0],"WavePosition":"s_1_wl_0_w_1_e_1"},{"HeroId":"YoYo","Power":2248,"Level":33,"GearLevel":4,"Loyalty":2,"RedStar":0,"Abilities":[3,3,2,1,0,0],"WavePosition":"s_1_wl_0_w_1_e_2"}]}]}],"OmitFromMetadata":false}